{
  "version": "0.0.1",
  "metrics": [
    {
      "capture_id": "6cada022-88d6-4a12-a469-415e84c5a3e4",
      "annotation_id": null,
      "sequence_id": "fd06cdf1-44f0-4c53-8739-c0eda6dc5436",
      "step": 0,
      "metric_definition": "51da3c27-369d-4929-aea6-d01614635ce2",
      "values": [
        {
          "label_id": 1,
          "label_name": "person",
          "count": 0
        }
      ]
    },
    {
      "capture_id": "6cada022-88d6-4a12-a469-415e84c5a3e4",
      "annotation_id": null,
      "sequence_id": "fd06cdf1-44f0-4c53-8739-c0eda6dc5436",
      "step": 0,
      "metric_definition": "5ba92024-b3b7-41a7-9d3f-c03a6a8ddd01",
      "values": []
    },
    {
      "capture_id": null,
      "annotation_id": null,
      "sequence_id": "00461c48-8853-4eb8-8777-f04f7760deeb",
      "step": 0,
      "metric_definition": "db1b258e-d1d0-41b6-8751-16f601a2e230",
      "values": [
        {
          "iteration": 31
        }
      ]
    },
    {
      "capture_id": null,
      "annotation_id": null,
      "sequence_id": "00461c48-8853-4eb8-8777-f04f7760deeb",
      "step": 0,
      "metric_definition": "c0b5e272-9715-4ea2-930e-cfe8cecf1b6e",
      "values": [{ "LightPositionX_DirectionalLightSun": 0,
                       "LightPositionY_DirectionalLightSun": 22,
                       "LightPositionZ_DirectionalLightSun": 14 }]
    },
    {
      "capture_id": null,
      "annotation_id": null,
      "sequence_id": "00461c48-8853-4eb8-8777-f04f7760deeb",
      "step": 0,
      "metric_definition": "317735b9-b4a4-4f6b-a4c9-eb846463a583",
      "values": [{ "LightRotationX_DirectionalLightSun": 29.83253,
                       "LightRotationY_DirectionalLightSun": 228.5944,
                       "LightRotationZ_DirectionalLightSun": 178.1064 }]
    },
    {
      "capture_id": null,
      "annotation_id": null,
      "sequence_id": "00461c48-8853-4eb8-8777-f04f7760deeb",
      "step": 0,
      "metric_definition": "1a709e09-81bd-43b5-b8f0-f3952a1af444",
      "values": [{ "LightIntensity_DirectionalLightSun": 10000 }]
    },
    {
      "capture_id": null,
      "annotation_id": null,
      "sequence_id": "00461c48-8853-4eb8-8777-f04f7760deeb",
      "step": 0,
      "metric_definition": "a640e390-fa13-4bb0-b2cd-1e0cb3f43eb9",
      "values": [{ "LightColorR_DirectionalLightSun": 1,
                       "LightColorG_DirectionalLightSun": 0.9568627,
                       "LightColorB_DirectionalLightSun": 0.8392157,
                       "LightColorA_DirectionalLightSun": 1 }]
    },
    {
      "capture_id": null,
      "annotation_id": null,
      "sequence_id": "00461c48-8853-4eb8-8777-f04f7760deeb",
      "step": 0,
      "metric_definition": "c0b5e272-9715-4ea2-930e-cfe8cecf1b6e",
      "values": [{ "LightPositionX_PointLight1": -10,
                       "LightPositionY_PointLight1": 0,
                       "LightPositionZ_PointLight1": 0 }]
    },
    {
      "capture_id": null,
      "annotation_id": null,
      "sequence_id": "00461c48-8853-4eb8-8777-f04f7760deeb",
      "step": 0,
      "metric_definition": "317735b9-b4a4-4f6b-a4c9-eb846463a583",
      "values": [{ "LightRotationX_PointLight1": 0,
                       "LightRotationY_PointLight1": 0,
                       "LightRotationZ_PointLight1": 0 }]
    },
    {
      "capture_id": null,
      "annotation_id": null,
      "sequence_id": "00461c48-8853-4eb8-8777-f04f7760deeb",
      "step": 0,
      "metric_definition": "1a709e09-81bd-43b5-b8f0-f3952a1af444",
      "values": [{ "LightIntensity_PointLight1": 27720.28 }]
    },
    {
      "capture_id": null,
      "annotation_id": null,
      "sequence_id": "00461c48-8853-4eb8-8777-f04f7760deeb",
      "step": 0,
      "metric_definition": "a640e390-fa13-4bb0-b2cd-1e0cb3f43eb9",
      "values": [{ "LightColorR_PointLight1": 0.7291009,
                       "LightColorG_PointLight1": 0.07801652,
                       "LightColorB_PointLight1": 0.8863391,
                       "LightColorA_PointLight1": 1 }]
    },
    {
      "capture_id": null,
      "annotation_id": null,
      "sequence_id": "00461c48-8853-4eb8-8777-f04f7760deeb",
      "step": 0,
      "metric_definition": "c0b5e272-9715-4ea2-930e-cfe8cecf1b6e",
      "values": [{ "LightPositionX_PointLight2": 10,
                       "LightPositionY_PointLight2": 0,
                       "LightPositionZ_PointLight2": 0 }]
    },
    {
      "capture_id": null,
      "annotation_id": null,
      "sequence_id": "00461c48-8853-4eb8-8777-f04f7760deeb",
      "step": 0,
      "metric_definition": "317735b9-b4a4-4f6b-a4c9-eb846463a583",
      "values": [{ "LightRotationX_PointLight2": 0,
                       "LightRotationY_PointLight2": 0,
                       "LightRotationZ_PointLight2": 0 }]
    },
    {
      "capture_id": null,
      "annotation_id": null,
      "sequence_id": "00461c48-8853-4eb8-8777-f04f7760deeb",
      "step": 0,
      "metric_definition": "1a709e09-81bd-43b5-b8f0-f3952a1af444",
      "values": [{ "LightIntensity_PointLight2": 44536.52 }]
    },
    {
      "capture_id": null,
      "annotation_id": null,
      "sequence_id": "00461c48-8853-4eb8-8777-f04f7760deeb",
      "step": 0,
      "metric_definition": "a640e390-fa13-4bb0-b2cd-1e0cb3f43eb9",
      "values": [{ "LightColorR_PointLight2": 0.1478488,
                       "LightColorG_PointLight2": 0.2329347,
                       "LightColorB_PointLight2": 0.7965108,
                       "LightColorA_PointLight2": 1 }]
    },
    {
      "capture_id": null,
      "annotation_id": null,
      "sequence_id": "00461c48-8853-4eb8-8777-f04f7760deeb",
      "step": 0,
      "metric_definition": "c0b5e272-9715-4ea2-930e-cfe8cecf1b6e",
      "values": [{ "LightPositionX_PointLight3": 0,
                       "LightPositionY_PointLight3": 10,
                       "LightPositionZ_PointLight3": 0 }]
    },
    {
      "capture_id": null,
      "annotation_id": null,
      "sequence_id": "00461c48-8853-4eb8-8777-f04f7760deeb",
      "step": 0,
      "metric_definition": "317735b9-b4a4-4f6b-a4c9-eb846463a583",
      "values": [{ "LightRotationX_PointLight3": 0,
                       "LightRotationY_PointLight3": 0,
                       "LightRotationZ_PointLight3": 270 }]
    },
    {
      "capture_id": null,
      "annotation_id": null,
      "sequence_id": "00461c48-8853-4eb8-8777-f04f7760deeb",
      "step": 0,
      "metric_definition": "1a709e09-81bd-43b5-b8f0-f3952a1af444",
      "values": [{ "LightIntensity_PointLight3": 6995.515 }]
    },
    {
      "capture_id": null,
      "annotation_id": null,
      "sequence_id": "00461c48-8853-4eb8-8777-f04f7760deeb",
      "step": 0,
      "metric_definition": "a640e390-fa13-4bb0-b2cd-1e0cb3f43eb9",
      "values": [{ "LightColorR_PointLight3": 0.1485808,
                       "LightColorG_PointLight3": 0.05981135,
                       "LightColorB_PointLight3": 0.9595383,
                       "LightColorA_PointLight3": 1 }]
    },
    {
      "capture_id": null,
      "annotation_id": null,
      "sequence_id": "00461c48-8853-4eb8-8777-f04f7760deeb",
      "step": 0,
      "metric_definition": "c0b5e272-9715-4ea2-930e-cfe8cecf1b6e",
      "values": [{ "LightPositionX_PointLight4": 0,
                       "LightPositionY_PointLight4": -11,
                       "LightPositionZ_PointLight4": 0 }]
    },
    {
      "capture_id": null,
      "annotation_id": null,
      "sequence_id": "00461c48-8853-4eb8-8777-f04f7760deeb",
      "step": 0,
      "metric_definition": "317735b9-b4a4-4f6b-a4c9-eb846463a583",
      "values": [{ "LightRotationX_PointLight4": 0,
                       "LightRotationY_PointLight4": 0,
                       "LightRotationZ_PointLight4": 270 }]
    },
    {
      "capture_id": null,
      "annotation_id": null,
      "sequence_id": "00461c48-8853-4eb8-8777-f04f7760deeb",
      "step": 0,
      "metric_definition": "1a709e09-81bd-43b5-b8f0-f3952a1af444",
      "values": [{ "LightIntensity_PointLight4": 15967.06 }]
    },
    {
      "capture_id": null,
      "annotation_id": null,
      "sequence_id": "00461c48-8853-4eb8-8777-f04f7760deeb",
      "step": 0,
      "metric_definition": "a640e390-fa13-4bb0-b2cd-1e0cb3f43eb9",
      "values": [{ "LightColorR_PointLight4": 0.8715296,
                       "LightColorG_PointLight4": 0.2051095,
                       "LightColorB_PointLight4": 0.8930968,
                       "LightColorA_PointLight4": 1 }]
    },
    {
      "capture_id": null,
      "annotation_id": null,
      "sequence_id": "00461c48-8853-4eb8-8777-f04f7760deeb",
      "step": 0,
      "metric_definition": "c0b5e272-9715-4ea2-930e-cfe8cecf1b6e",
      "values": [{ "LightPositionX_PointLight5": 0,
                       "LightPositionY_PointLight5": 0,
                       "LightPositionZ_PointLight5": 10 }]
    },
    {
      "capture_id": null,
      "annotation_id": null,
      "sequence_id": "00461c48-8853-4eb8-8777-f04f7760deeb",
      "step": 0,
      "metric_definition": "317735b9-b4a4-4f6b-a4c9-eb846463a583",
      "values": [{ "LightRotationX_PointLight5": 90,
                       "LightRotationY_PointLight5": 89.99998,
                       "LightRotationZ_PointLight5": 0 }]
    },
    {
      "capture_id": null,
      "annotation_id": null,
      "sequence_id": "00461c48-8853-4eb8-8777-f04f7760deeb",
      "step": 0,
      "metric_definition": "1a709e09-81bd-43b5-b8f0-f3952a1af444",
      "values": [{ "LightIntensity_PointLight5": 6631.631 }]
    },
    {
      "capture_id": null,
      "annotation_id": null,
      "sequence_id": "00461c48-8853-4eb8-8777-f04f7760deeb",
      "step": 0,
      "metric_definition": "a640e390-fa13-4bb0-b2cd-1e0cb3f43eb9",
      "values": [{ "LightColorR_PointLight5": 0.5682923,
                       "LightColorG_PointLight5": 0.4552559,
                       "LightColorB_PointLight5": 0.7904358,
                       "LightColorA_PointLight5": 1 }]
    },
    {
      "capture_id": null,
      "annotation_id": null,
      "sequence_id": "00461c48-8853-4eb8-8777-f04f7760deeb",
      "step": 0,
      "metric_definition": "c0b5e272-9715-4ea2-930e-cfe8cecf1b6e",
      "values": [{ "LightPositionX_PointLight6": 0,
                       "LightPositionY_PointLight6": 0,
                       "LightPositionZ_PointLight6": -7 }]
    },
    {
      "capture_id": null,
      "annotation_id": null,
      "sequence_id": "00461c48-8853-4eb8-8777-f04f7760deeb",
      "step": 0,
      "metric_definition": "317735b9-b4a4-4f6b-a4c9-eb846463a583",
      "values": [{ "LightRotationX_PointLight6": 90,
                       "LightRotationY_PointLight6": 89.99998,
                       "LightRotationZ_PointLight6": 0 }]
    },
    {
      "capture_id": null,
      "annotation_id": null,
      "sequence_id": "00461c48-8853-4eb8-8777-f04f7760deeb",
      "step": 0,
      "metric_definition": "1a709e09-81bd-43b5-b8f0-f3952a1af444",
      "values": [{ "LightIntensity_PointLight6": 23659.32 }]
    },
    {
      "capture_id": null,
      "annotation_id": null,
      "sequence_id": "00461c48-8853-4eb8-8777-f04f7760deeb",
      "step": 0,
      "metric_definition": "a640e390-fa13-4bb0-b2cd-1e0cb3f43eb9",
      "values": [{ "LightColorR_PointLight6": 0.8482189,
                       "LightColorG_PointLight6": 0.3012016,
                       "LightColorB_PointLight6": 0.6993172,
                       "LightColorA_PointLight6": 1 }]
    },
    {
      "capture_id": null,
      "annotation_id": null,
      "sequence_id": "00461c48-8853-4eb8-8777-f04f7760deeb",
      "step": 0,
      "metric_definition": "c0b5e272-9715-4ea2-930e-cfe8cecf1b6e",
      "values": [{ "LightPositionX_PointLightSceneMoving": -0.787802,
                       "LightPositionY_PointLightSceneMoving": 10.20765,
                       "LightPositionZ_PointLightSceneMoving": 4.111819 }]
    },
    {
      "capture_id": null,
      "annotation_id": null,
      "sequence_id": "00461c48-8853-4eb8-8777-f04f7760deeb",
      "step": 0,
      "metric_definition": "317735b9-b4a4-4f6b-a4c9-eb846463a583",
      "values": [{ "LightRotationX_PointLightSceneMoving": 344.9572,
                       "LightRotationY_PointLightSceneMoving": 26.6823,
                       "LightRotationZ_PointLightSceneMoving": 28.5166 }]
    },
    {
      "capture_id": null,
      "annotation_id": null,
      "sequence_id": "00461c48-8853-4eb8-8777-f04f7760deeb",
      "step": 0,
      "metric_definition": "1a709e09-81bd-43b5-b8f0-f3952a1af444",
      "values": [{ "LightIntensity_PointLightSceneMoving": 48438.22 }]
    },
    {
      "capture_id": null,
      "annotation_id": null,
      "sequence_id": "00461c48-8853-4eb8-8777-f04f7760deeb",
      "step": 0,
      "metric_definition": "a640e390-fa13-4bb0-b2cd-1e0cb3f43eb9",
      "values": [{ "LightColorR_PointLightSceneMoving": 0.6374079,
                       "LightColorG_PointLightSceneMoving": 0.7247959,
                       "LightColorB_PointLightSceneMoving": 0.687766,
                       "LightColorA_PointLightSceneMoving": 1 }]
    },
    {
      "capture_id": null,
      "annotation_id": null,
      "sequence_id": "00461c48-8853-4eb8-8777-f04f7760deeb",
      "step": 0,
      "metric_definition": "1529faeb-863f-40c2-840f-5fe4221c1065",
      "values": [{ "CameraPositionX": -1.433911, "CameraPositionY": 3.420065, "CameraPositionZ": 18.75633 }]
    },
    {
      "capture_id": null,
      "annotation_id": null,
      "sequence_id": "00461c48-8853-4eb8-8777-f04f7760deeb",
      "step": 0,
      "metric_definition": "5199deef-2eb0-42fe-b00d-1d2418aedaff",
      "values": [{ "CameraRotationX": 355.4793, "CameraRotationY": 176.196, "CameraRotationZ": 4.23758 }]
    },
    {
      "capture_id": null,
      "annotation_id": null,
      "sequence_id": "00461c48-8853-4eb8-8777-f04f7760deeb",
      "step": 0,
      "metric_definition": "42e7fa88-084b-423d-ba6e-830c711383e1",
      "values": [{ "CameraFieldOfView": 34.93714 }]
    },
    {
      "capture_id": null,
      "annotation_id": null,
      "sequence_id": "00461c48-8853-4eb8-8777-f04f7760deeb",
      "step": 0,
      "metric_definition": "11aa1dfc-3495-467c-a998-71d9bfe6980e",
      "values": [{ "CameraFocalLength": 15.41981 }]
    },
    {
      "capture_id": "42682b33-8502-4223-bdf4-4353a164422a",
      "annotation_id": null,
      "sequence_id": "00461c48-8853-4eb8-8777-f04f7760deeb",
      "step": 0,
      "metric_definition": "51da3c27-369d-4929-aea6-d01614635ce2",
      "values": [
        {
          "label_id": 1,
          "label_name": "person",
          "count": 11
        }
      ]
    },
    {
      "capture_id": "42682b33-8502-4223-bdf4-4353a164422a",
      "annotation_id": null,
      "sequence_id": "00461c48-8853-4eb8-8777-f04f7760deeb",
      "step": 0,
      "metric_definition": "5ba92024-b3b7-41a7-9d3f-c03a6a8ddd01",
      "values": [
        {
          "label_id": 1,
          "instance_id": 15,
          "instance_color": {
            "r": 0,
            "g": 22,
            "b": 255,
            "a": 255
          },
          "visible_pixels": 1832
        },
        {
          "label_id": 1,
          "instance_id": 22,
          "instance_color": {
            "r": 255,
            "g": 0,
            "b": 33,
            "a": 255
          },
          "visible_pixels": 2232
        },
        {
          "label_id": 1,
          "instance_id": 27,
          "instance_color": {
            "r": 255,
            "g": 105,
            "b": 0,
            "a": 255
          },
          "visible_pixels": 492
        },
        {
          "label_id": 1,
          "instance_id": 58,
          "instance_color": {
            "r": 161,
            "g": 255,
            "b": 0,
            "a": 255
          },
          "visible_pixels": 5839
        },
        {
          "label_id": 1,
          "instance_id": 16,
          "instance_color": {
            "r": 96,
            "g": 255,
            "b": 0,
            "a": 255
          },
          "visible_pixels": 14043
        },
        {
          "label_id": 1,
          "instance_id": 29,
          "instance_color": {
            "r": 43,
            "g": 255,
            "b": 0,
            "a": 255
          },
          "visible_pixels": 2059
        },
        {
          "label_id": 1,
          "instance_id": 31,
          "instance_color": {
            "r": 0,
            "g": 192,
            "b": 255,
            "a": 255
          },
          "visible_pixels": 391
        },
        {
          "label_id": 1,
          "instance_id": 17,
          "instance_color": {
            "r": 255,
            "g": 0,
            "b": 171,
            "a": 255
          },
          "visible_pixels": 463
        },
        {
          "label_id": 1,
          "instance_id": 56,
          "instance_color": {
            "r": 255,
            "g": 0,
            "b": 12,
            "a": 255
          },
          "visible_pixels": 2652
        },
        {
          "label_id": 1,
          "instance_id": 9,
          "instance_color": {
            "r": 255,
            "g": 0,
            "b": 85,
            "a": 255
          },
          "visible_pixels": 5247
        },
        {
          "label_id": 1,
          "instance_id": 2,
          "instance_color": {
            "r": 0,
            "g": 74,
            "b": 255,
            "a": 255
          },
          "visible_pixels": 302
        }
      ]
    },
    {
      "capture_id": null,
      "annotation_id": null,
      "sequence_id": "8f749795-40a1-484c-b27c-0592b95a3e5e",
      "step": 0,
      "metric_definition": "db1b258e-d1d0-41b6-8751-16f601a2e230",
      "values": [
        {
          "iteration": 32
        }
      ]
    },
    {
      "capture_id": null,
      "annotation_id": null,
      "sequence_id": "8f749795-40a1-484c-b27c-0592b95a3e5e",
      "step": 0,
      "metric_definition": "c0b5e272-9715-4ea2-930e-cfe8cecf1b6e",
      "values": [{ "LightPositionX_DirectionalLightSun": 0,
                       "LightPositionY_DirectionalLightSun": 22,
                       "LightPositionZ_DirectionalLightSun": 14 }]
    },
    {
      "capture_id": null,
      "annotation_id": null,
      "sequence_id": "8f749795-40a1-484c-b27c-0592b95a3e5e",
      "step": 0,
      "metric_definition": "317735b9-b4a4-4f6b-a4c9-eb846463a583",
      "values": [{ "LightRotationX_DirectionalLightSun": 336.1686,
                       "LightRotationY_DirectionalLightSun": 170.041,
                       "LightRotationZ_DirectionalLightSun": 1.837973 }]
    },
    {
      "capture_id": null,
      "annotation_id": null,
      "sequence_id": "8f749795-40a1-484c-b27c-0592b95a3e5e",
      "step": 0,
      "metric_definition": "1a709e09-81bd-43b5-b8f0-f3952a1af444",
      "values": [{ "LightIntensity_DirectionalLightSun": 10000 }]
    },
    {
      "capture_id": null,
      "annotation_id": null,
      "sequence_id": "8f749795-40a1-484c-b27c-0592b95a3e5e",
      "step": 0,
      "metric_definition": "a640e390-fa13-4bb0-b2cd-1e0cb3f43eb9",
      "values": [{ "LightColorR_DirectionalLightSun": 1,
                       "LightColorG_DirectionalLightSun": 0.9568627,
                       "LightColorB_DirectionalLightSun": 0.8392157,
                       "LightColorA_DirectionalLightSun": 1 }]
    },
    {
      "capture_id": null,
      "annotation_id": null,
      "sequence_id": "8f749795-40a1-484c-b27c-0592b95a3e5e",
      "step": 0,
      "metric_definition": "c0b5e272-9715-4ea2-930e-cfe8cecf1b6e",
      "values": [{ "LightPositionX_PointLight1": -10,
                       "LightPositionY_PointLight1": 0,
                       "LightPositionZ_PointLight1": 0 }]
    },
    {
      "capture_id": null,
      "annotation_id": null,
      "sequence_id": "8f749795-40a1-484c-b27c-0592b95a3e5e",
      "step": 0,
      "metric_definition": "317735b9-b4a4-4f6b-a4c9-eb846463a583",
      "values": [{ "LightRotationX_PointLight1": 0,
                       "LightRotationY_PointLight1": 0,
                       "LightRotationZ_PointLight1": 0 }]
    },
    {
      "capture_id": null,
      "annotation_id": null,
      "sequence_id": "8f749795-40a1-484c-b27c-0592b95a3e5e",
      "step": 0,
      "metric_definition": "1a709e09-81bd-43b5-b8f0-f3952a1af444",
      "values": [{ "LightIntensity_PointLight1": 34027.69 }]
    },
    {
      "capture_id": null,
      "annotation_id": null,
      "sequence_id": "8f749795-40a1-484c-b27c-0592b95a3e5e",
      "step": 0,
      "metric_definition": "a640e390-fa13-4bb0-b2cd-1e0cb3f43eb9",
      "values": [{ "LightColorR_PointLight1": 0.9740611,
                       "LightColorG_PointLight1": 0.9083328,
                       "LightColorB_PointLight1": 0.000174284,
                       "LightColorA_PointLight1": 1 }]
    },
    {
      "capture_id": null,
      "annotation_id": null,
      "sequence_id": "8f749795-40a1-484c-b27c-0592b95a3e5e",
      "step": 0,
      "metric_definition": "c0b5e272-9715-4ea2-930e-cfe8cecf1b6e",
      "values": [{ "LightPositionX_PointLight2": 10,
                       "LightPositionY_PointLight2": 0,
                       "LightPositionZ_PointLight2": 0 }]
    },
    {
      "capture_id": null,
      "annotation_id": null,
      "sequence_id": "8f749795-40a1-484c-b27c-0592b95a3e5e",
      "step": 0,
      "metric_definition": "317735b9-b4a4-4f6b-a4c9-eb846463a583",
      "values": [{ "LightRotationX_PointLight2": 0,
                       "LightRotationY_PointLight2": 0,
                       "LightRotationZ_PointLight2": 0 }]
    },
    {
      "capture_id": null,
      "annotation_id": null,
      "sequence_id": "8f749795-40a1-484c-b27c-0592b95a3e5e",
      "step": 0,
      "metric_definition": "1a709e09-81bd-43b5-b8f0-f3952a1af444",
      "values": [{ "LightIntensity_PointLight2": 31536.39 }]
    },
    {
      "capture_id": null,
      "annotation_id": null,
      "sequence_id": "8f749795-40a1-484c-b27c-0592b95a3e5e",
      "step": 0,
      "metric_definition": "a640e390-fa13-4bb0-b2cd-1e0cb3f43eb9",
      "values": [{ "LightColorR_PointLight2": 0.2103105,
                       "LightColorG_PointLight2": 0.2736247,
                       "LightColorB_PointLight2": 0.6686344,
                       "LightColorA_PointLight2": 1 }]
    },
    {
      "capture_id": null,
      "annotation_id": null,
      "sequence_id": "8f749795-40a1-484c-b27c-0592b95a3e5e",
      "step": 0,
      "metric_definition": "c0b5e272-9715-4ea2-930e-cfe8cecf1b6e",
      "values": [{ "LightPositionX_PointLight3": 0,
                       "LightPositionY_PointLight3": 10,
                       "LightPositionZ_PointLight3": 0 }]
    },
    {
      "capture_id": null,
      "annotation_id": null,
      "sequence_id": "8f749795-40a1-484c-b27c-0592b95a3e5e",
      "step": 0,
      "metric_definition": "317735b9-b4a4-4f6b-a4c9-eb846463a583",
      "values": [{ "LightRotationX_PointLight3": 0,
                       "LightRotationY_PointLight3": 0,
                       "LightRotationZ_PointLight3": 270 }]
    },
    {
      "capture_id": null,
      "annotation_id": null,
      "sequence_id": "8f749795-40a1-484c-b27c-0592b95a3e5e",
      "step": 0,
      "metric_definition": "1a709e09-81bd-43b5-b8f0-f3952a1af444",
      "values": [{ "LightIntensity_PointLight3": 21874.47 }]
    },
    {
      "capture_id": null,
      "annotation_id": null,
      "sequence_id": "8f749795-40a1-484c-b27c-0592b95a3e5e",
      "step": 0,
      "metric_definition": "a640e390-fa13-4bb0-b2cd-1e0cb3f43eb9",
      "values": [{ "LightColorR_PointLight3": 0.2634981,
                       "LightColorG_PointLight3": 0.5262699,
                       "LightColorB_PointLight3": 0.5922055,
                       "LightColorA_PointLight3": 1 }]
    },
    {
      "capture_id": null,
      "annotation_id": null,
      "sequence_id": "8f749795-40a1-484c-b27c-0592b95a3e5e",
      "step": 0,
      "metric_definition": "c0b5e272-9715-4ea2-930e-cfe8cecf1b6e",
      "values": [{ "LightPositionX_PointLight4": 0,
                       "LightPositionY_PointLight4": -11,
                       "LightPositionZ_PointLight4": 0 }]
    },
    {
      "capture_id": null,
      "annotation_id": null,
      "sequence_id": "8f749795-40a1-484c-b27c-0592b95a3e5e",
      "step": 0,
      "metric_definition": "317735b9-b4a4-4f6b-a4c9-eb846463a583",
      "values": [{ "LightRotationX_PointLight4": 0,
                       "LightRotationY_PointLight4": 0,
                       "LightRotationZ_PointLight4": 270 }]
    },
    {
      "capture_id": null,
      "annotation_id": null,
      "sequence_id": "8f749795-40a1-484c-b27c-0592b95a3e5e",
      "step": 0,
      "metric_definition": "1a709e09-81bd-43b5-b8f0-f3952a1af444",
      "values": [{ "LightIntensity_PointLight4": 23340.52 }]
    },
    {
      "capture_id": null,
      "annotation_id": null,
      "sequence_id": "8f749795-40a1-484c-b27c-0592b95a3e5e",
      "step": 0,
      "metric_definition": "a640e390-fa13-4bb0-b2cd-1e0cb3f43eb9",
      "values": [{ "LightColorR_PointLight4": 0.6903056,
                       "LightColorG_PointLight4": 0.732999,
                       "LightColorB_PointLight4": 0.9356545,
                       "LightColorA_PointLight4": 1 }]
    },
    {
      "capture_id": null,
      "annotation_id": null,
      "sequence_id": "8f749795-40a1-484c-b27c-0592b95a3e5e",
      "step": 0,
      "metric_definition": "c0b5e272-9715-4ea2-930e-cfe8cecf1b6e",
      "values": [{ "LightPositionX_PointLight5": 0,
                       "LightPositionY_PointLight5": 0,
                       "LightPositionZ_PointLight5": 10 }]
    },
    {
      "capture_id": null,
      "annotation_id": null,
      "sequence_id": "8f749795-40a1-484c-b27c-0592b95a3e5e",
      "step": 0,
      "metric_definition": "317735b9-b4a4-4f6b-a4c9-eb846463a583",
      "values": [{ "LightRotationX_PointLight5": 90,
                       "LightRotationY_PointLight5": 89.99998,
                       "LightRotationZ_PointLight5": 0 }]
    },
    {
      "capture_id": null,
      "annotation_id": null,
      "sequence_id": "8f749795-40a1-484c-b27c-0592b95a3e5e",
      "step": 0,
      "metric_definition": "1a709e09-81bd-43b5-b8f0-f3952a1af444",
      "values": [{ "LightIntensity_PointLight5": 21931.11 }]
    },
    {
      "capture_id": null,
      "annotation_id": null,
      "sequence_id": "8f749795-40a1-484c-b27c-0592b95a3e5e",
      "step": 0,
      "metric_definition": "a640e390-fa13-4bb0-b2cd-1e0cb3f43eb9",
      "values": [{ "LightColorR_PointLight5": 0.6941342,
                       "LightColorG_PointLight5": 0.5857992,
                       "LightColorB_PointLight5": 0.2487278,
                       "LightColorA_PointLight5": 1 }]
    },
    {
      "capture_id": null,
      "annotation_id": null,
      "sequence_id": "8f749795-40a1-484c-b27c-0592b95a3e5e",
      "step": 0,
      "metric_definition": "c0b5e272-9715-4ea2-930e-cfe8cecf1b6e",
      "values": [{ "LightPositionX_PointLight6": 0,
                       "LightPositionY_PointLight6": 0,
                       "LightPositionZ_PointLight6": -7 }]
    },
    {
      "capture_id": null,
      "annotation_id": null,
      "sequence_id": "8f749795-40a1-484c-b27c-0592b95a3e5e",
      "step": 0,
      "metric_definition": "317735b9-b4a4-4f6b-a4c9-eb846463a583",
      "values": [{ "LightRotationX_PointLight6": 90,
                       "LightRotationY_PointLight6": 89.99998,
                       "LightRotationZ_PointLight6": 0 }]
    },
    {
      "capture_id": null,
      "annotation_id": null,
      "sequence_id": "8f749795-40a1-484c-b27c-0592b95a3e5e",
      "step": 0,
      "metric_definition": "1a709e09-81bd-43b5-b8f0-f3952a1af444",
      "values": [{ "LightIntensity_PointLight6": 38725.9 }]
    },
    {
      "capture_id": null,
      "annotation_id": null,
      "sequence_id": "8f749795-40a1-484c-b27c-0592b95a3e5e",
      "step": 0,
      "metric_definition": "a640e390-fa13-4bb0-b2cd-1e0cb3f43eb9",
      "values": [{ "LightColorR_PointLight6": 0.5998251,
                       "LightColorG_PointLight6": 0.7025698,
                       "LightColorB_PointLight6": 0.04526651,
                       "LightColorA_PointLight6": 1 }]
    },
    {
      "capture_id": null,
      "annotation_id": null,
      "sequence_id": "8f749795-40a1-484c-b27c-0592b95a3e5e",
      "step": 0,
      "metric_definition": "c0b5e272-9715-4ea2-930e-cfe8cecf1b6e",
      "values": [{ "LightPositionX_PointLightSceneMoving": 0.6704248,
                       "LightPositionY_PointLightSceneMoving": 4.09549,
                       "LightPositionZ_PointLightSceneMoving": 1.780854 }]
    },
    {
      "capture_id": null,
      "annotation_id": null,
      "sequence_id": "8f749795-40a1-484c-b27c-0592b95a3e5e",
      "step": 0,
      "metric_definition": "317735b9-b4a4-4f6b-a4c9-eb846463a583",
      "values": [{ "LightRotationX_PointLightSceneMoving": 310.8346,
                       "LightRotationY_PointLightSceneMoving": 328.039,
                       "LightRotationZ_PointLightSceneMoving": 16.50133 }]
    },
    {
      "capture_id": null,
      "annotation_id": null,
      "sequence_id": "8f749795-40a1-484c-b27c-0592b95a3e5e",
      "step": 0,
      "metric_definition": "1a709e09-81bd-43b5-b8f0-f3952a1af444",
      "values": [{ "LightIntensity_PointLightSceneMoving": 29937.91 }]
    },
    {
      "capture_id": null,
      "annotation_id": null,
      "sequence_id": "8f749795-40a1-484c-b27c-0592b95a3e5e",
      "step": 0,
      "metric_definition": "a640e390-fa13-4bb0-b2cd-1e0cb3f43eb9",
      "values": [{ "LightColorR_PointLightSceneMoving": 0.3999408,
                       "LightColorG_PointLightSceneMoving": 0.1387277,
                       "LightColorB_PointLightSceneMoving": 0.2176397,
                       "LightColorA_PointLightSceneMoving": 1 }]
    },
    {
      "capture_id": null,
      "annotation_id": null,
      "sequence_id": "8f749795-40a1-484c-b27c-0592b95a3e5e",
      "step": 0,
      "metric_definition": "1529faeb-863f-40c2-840f-5fe4221c1065",
      "values": [{ "CameraPositionX": -1.744948, "CameraPositionY": -3.75196, "CameraPositionZ": 12.13344 }]
    },
    {
      "capture_id": null,
      "annotation_id": null,
      "sequence_id": "8f749795-40a1-484c-b27c-0592b95a3e5e",
      "step": 0,
      "metric_definition": "5199deef-2eb0-42fe-b00d-1d2418aedaff",
      "values": [{ "CameraRotationX": 3.330296, "CameraRotationY": 181.5509, "CameraRotationZ": 358.7066 }]
    },
    {
      "capture_id": null,
      "annotation_id": null,
      "sequence_id": "8f749795-40a1-484c-b27c-0592b95a3e5e",
      "step": 0,
      "metric_definition": "42e7fa88-084b-423d-ba6e-830c711383e1",
      "values": [{ "CameraFieldOfView": 27.77172 }]
    },
    {
      "capture_id": null,
      "annotation_id": null,
      "sequence_id": "8f749795-40a1-484c-b27c-0592b95a3e5e",
      "step": 0,
      "metric_definition": "11aa1dfc-3495-467c-a998-71d9bfe6980e",
      "values": [{ "CameraFocalLength": 4.745457 }]
    },
    {
      "capture_id": "9cdfc1dc-f05c-46ce-8f49-d52eb5eea791",
      "annotation_id": null,
      "sequence_id": "8f749795-40a1-484c-b27c-0592b95a3e5e",
      "step": 0,
      "metric_definition": "51da3c27-369d-4929-aea6-d01614635ce2",
      "values": [
        {
          "label_id": 1,
          "label_name": "person",
          "count": 4
        }
      ]
    },
    {
      "capture_id": "9cdfc1dc-f05c-46ce-8f49-d52eb5eea791",
      "annotation_id": null,
      "sequence_id": "8f749795-40a1-484c-b27c-0592b95a3e5e",
      "step": 0,
      "metric_definition": "5ba92024-b3b7-41a7-9d3f-c03a6a8ddd01",
      "values": [
        {
          "label_id": 1,
          "instance_id": 5,
          "instance_color": {
            "r": 0,
            "g": 255,
            "b": 212,
            "a": 255
          },
          "visible_pixels": 2008
        },
        {
          "label_id": 1,
          "instance_id": 22,
          "instance_color": {
            "r": 255,
            "g": 0,
            "b": 33,
            "a": 255
          },
          "visible_pixels": 2708
        },
        {
          "label_id": 1,
          "instance_id": 43,
          "instance_color": {
            "r": 255,
            "g": 0,
            "b": 65,
            "a": 255
          },
          "visible_pixels": 26533
        },
        {
          "label_id": 1,
          "instance_id": 48,
          "instance_color": {
            "r": 255,
            "g": 73,
            "b": 0,
            "a": 255
          },
          "visible_pixels": 1573
        }
      ]
    },
    {
      "capture_id": null,
      "annotation_id": null,
      "sequence_id": "aaf0f9c2-6c84-47b1-8209-41c3bbd60d46",
      "step": 0,
      "metric_definition": "db1b258e-d1d0-41b6-8751-16f601a2e230",
      "values": [
        {
          "iteration": 33
        }
      ]
    },
    {
      "capture_id": null,
      "annotation_id": null,
      "sequence_id": "aaf0f9c2-6c84-47b1-8209-41c3bbd60d46",
      "step": 0,
      "metric_definition": "c0b5e272-9715-4ea2-930e-cfe8cecf1b6e",
      "values": [{ "LightPositionX_DirectionalLightSun": 0,
                       "LightPositionY_DirectionalLightSun": 22,
                       "LightPositionZ_DirectionalLightSun": 14 }]
    },
    {
      "capture_id": null,
      "annotation_id": null,
      "sequence_id": "aaf0f9c2-6c84-47b1-8209-41c3bbd60d46",
      "step": 0,
      "metric_definition": "317735b9-b4a4-4f6b-a4c9-eb846463a583",
      "values": [{ "LightRotationX_DirectionalLightSun": 328.2176,
                       "LightRotationY_DirectionalLightSun": 238.8132,
                       "LightRotationZ_DirectionalLightSun": 353.8848 }]
    },
    {
      "capture_id": null,
      "annotation_id": null,
      "sequence_id": "aaf0f9c2-6c84-47b1-8209-41c3bbd60d46",
      "step": 0,
      "metric_definition": "1a709e09-81bd-43b5-b8f0-f3952a1af444",
      "values": [{ "LightIntensity_DirectionalLightSun": 10000 }]
    },
    {
      "capture_id": null,
      "annotation_id": null,
      "sequence_id": "aaf0f9c2-6c84-47b1-8209-41c3bbd60d46",
      "step": 0,
      "metric_definition": "a640e390-fa13-4bb0-b2cd-1e0cb3f43eb9",
      "values": [{ "LightColorR_DirectionalLightSun": 1,
                       "LightColorG_DirectionalLightSun": 0.9568627,
                       "LightColorB_DirectionalLightSun": 0.8392157,
                       "LightColorA_DirectionalLightSun": 1 }]
    },
    {
      "capture_id": null,
      "annotation_id": null,
      "sequence_id": "aaf0f9c2-6c84-47b1-8209-41c3bbd60d46",
      "step": 0,
      "metric_definition": "c0b5e272-9715-4ea2-930e-cfe8cecf1b6e",
      "values": [{ "LightPositionX_PointLight1": -10,
                       "LightPositionY_PointLight1": 0,
                       "LightPositionZ_PointLight1": 0 }]
    },
    {
      "capture_id": null,
      "annotation_id": null,
      "sequence_id": "aaf0f9c2-6c84-47b1-8209-41c3bbd60d46",
      "step": 0,
      "metric_definition": "317735b9-b4a4-4f6b-a4c9-eb846463a583",
      "values": [{ "LightRotationX_PointLight1": 0,
                       "LightRotationY_PointLight1": 0,
                       "LightRotationZ_PointLight1": 0 }]
    },
    {
      "capture_id": null,
      "annotation_id": null,
      "sequence_id": "aaf0f9c2-6c84-47b1-8209-41c3bbd60d46",
      "step": 0,
      "metric_definition": "1a709e09-81bd-43b5-b8f0-f3952a1af444",
      "values": [{ "LightIntensity_PointLight1": 35219.84 }]
    },
    {
      "capture_id": null,
      "annotation_id": null,
      "sequence_id": "aaf0f9c2-6c84-47b1-8209-41c3bbd60d46",
      "step": 0,
      "metric_definition": "a640e390-fa13-4bb0-b2cd-1e0cb3f43eb9",
      "values": [{ "LightColorR_PointLight1": 0.3624589,
                       "LightColorG_PointLight1": 0.3347425,
                       "LightColorB_PointLight1": 0.8148638,
                       "LightColorA_PointLight1": 1 }]
    },
    {
      "capture_id": null,
      "annotation_id": null,
      "sequence_id": "aaf0f9c2-6c84-47b1-8209-41c3bbd60d46",
      "step": 0,
      "metric_definition": "c0b5e272-9715-4ea2-930e-cfe8cecf1b6e",
      "values": [{ "LightPositionX_PointLight2": 10,
                       "LightPositionY_PointLight2": 0,
                       "LightPositionZ_PointLight2": 0 }]
    },
    {
      "capture_id": null,
      "annotation_id": null,
      "sequence_id": "aaf0f9c2-6c84-47b1-8209-41c3bbd60d46",
      "step": 0,
      "metric_definition": "317735b9-b4a4-4f6b-a4c9-eb846463a583",
      "values": [{ "LightRotationX_PointLight2": 0,
                       "LightRotationY_PointLight2": 0,
                       "LightRotationZ_PointLight2": 0 }]
    },
    {
      "capture_id": null,
      "annotation_id": null,
      "sequence_id": "aaf0f9c2-6c84-47b1-8209-41c3bbd60d46",
      "step": 0,
      "metric_definition": "1a709e09-81bd-43b5-b8f0-f3952a1af444",
      "values": [{ "LightIntensity_PointLight2": 13873.99 }]
    },
    {
      "capture_id": null,
      "annotation_id": null,
      "sequence_id": "aaf0f9c2-6c84-47b1-8209-41c3bbd60d46",
      "step": 0,
      "metric_definition": "a640e390-fa13-4bb0-b2cd-1e0cb3f43eb9",
      "values": [{ "LightColorR_PointLight2": 0.6054714,
                       "LightColorG_PointLight2": 0.4468521,
                       "LightColorB_PointLight2": 0.3142321,
                       "LightColorA_PointLight2": 1 }]
    },
    {
      "capture_id": null,
      "annotation_id": null,
      "sequence_id": "aaf0f9c2-6c84-47b1-8209-41c3bbd60d46",
      "step": 0,
      "metric_definition": "c0b5e272-9715-4ea2-930e-cfe8cecf1b6e",
      "values": [{ "LightPositionX_PointLight3": 0,
                       "LightPositionY_PointLight3": 10,
                       "LightPositionZ_PointLight3": 0 }]
    },
    {
      "capture_id": null,
      "annotation_id": null,
      "sequence_id": "aaf0f9c2-6c84-47b1-8209-41c3bbd60d46",
      "step": 0,
      "metric_definition": "317735b9-b4a4-4f6b-a4c9-eb846463a583",
      "values": [{ "LightRotationX_PointLight3": 0,
                       "LightRotationY_PointLight3": 0,
                       "LightRotationZ_PointLight3": 270 }]
    },
    {
      "capture_id": null,
      "annotation_id": null,
      "sequence_id": "aaf0f9c2-6c84-47b1-8209-41c3bbd60d46",
      "step": 0,
      "metric_definition": "1a709e09-81bd-43b5-b8f0-f3952a1af444",
      "values": [{ "LightIntensity_PointLight3": 25275.89 }]
    },
    {
      "capture_id": null,
      "annotation_id": null,
      "sequence_id": "aaf0f9c2-6c84-47b1-8209-41c3bbd60d46",
      "step": 0,
      "metric_definition": "a640e390-fa13-4bb0-b2cd-1e0cb3f43eb9",
      "values": [{ "LightColorR_PointLight3": 0.5364056,
                       "LightColorG_PointLight3": 0.9453071,
                       "LightColorB_PointLight3": 0.7920108,
                       "LightColorA_PointLight3": 1 }]
    },
    {
      "capture_id": null,
      "annotation_id": null,
      "sequence_id": "aaf0f9c2-6c84-47b1-8209-41c3bbd60d46",
      "step": 0,
      "metric_definition": "c0b5e272-9715-4ea2-930e-cfe8cecf1b6e",
      "values": [{ "LightPositionX_PointLight4": 0,
                       "LightPositionY_PointLight4": -11,
                       "LightPositionZ_PointLight4": 0 }]
    },
    {
      "capture_id": null,
      "annotation_id": null,
      "sequence_id": "aaf0f9c2-6c84-47b1-8209-41c3bbd60d46",
      "step": 0,
      "metric_definition": "317735b9-b4a4-4f6b-a4c9-eb846463a583",
      "values": [{ "LightRotationX_PointLight4": 0,
                       "LightRotationY_PointLight4": 0,
                       "LightRotationZ_PointLight4": 270 }]
    },
    {
      "capture_id": null,
      "annotation_id": null,
      "sequence_id": "aaf0f9c2-6c84-47b1-8209-41c3bbd60d46",
      "step": 0,
      "metric_definition": "1a709e09-81bd-43b5-b8f0-f3952a1af444",
      "values": [{ "LightIntensity_PointLight4": 12856.74 }]
    },
    {
      "capture_id": null,
      "annotation_id": null,
      "sequence_id": "aaf0f9c2-6c84-47b1-8209-41c3bbd60d46",
      "step": 0,
      "metric_definition": "a640e390-fa13-4bb0-b2cd-1e0cb3f43eb9",
      "values": [{ "LightColorR_PointLight4": 0.1466653,
                       "LightColorG_PointLight4": 0.8970059,
                       "LightColorB_PointLight4": 0.1876787,
                       "LightColorA_PointLight4": 1 }]
    },
    {
      "capture_id": null,
      "annotation_id": null,
      "sequence_id": "aaf0f9c2-6c84-47b1-8209-41c3bbd60d46",
      "step": 0,
      "metric_definition": "c0b5e272-9715-4ea2-930e-cfe8cecf1b6e",
      "values": [{ "LightPositionX_PointLight5": 0,
                       "LightPositionY_PointLight5": 0,
                       "LightPositionZ_PointLight5": 10 }]
    },
    {
      "capture_id": null,
      "annotation_id": null,
      "sequence_id": "aaf0f9c2-6c84-47b1-8209-41c3bbd60d46",
      "step": 0,
      "metric_definition": "317735b9-b4a4-4f6b-a4c9-eb846463a583",
      "values": [{ "LightRotationX_PointLight5": 90,
                       "LightRotationY_PointLight5": 89.99998,
                       "LightRotationZ_PointLight5": 0 }]
    },
    {
      "capture_id": null,
      "annotation_id": null,
      "sequence_id": "aaf0f9c2-6c84-47b1-8209-41c3bbd60d46",
      "step": 0,
      "metric_definition": "1a709e09-81bd-43b5-b8f0-f3952a1af444",
      "values": [{ "LightIntensity_PointLight5": 42487.42 }]
    },
    {
      "capture_id": null,
      "annotation_id": null,
      "sequence_id": "aaf0f9c2-6c84-47b1-8209-41c3bbd60d46",
      "step": 0,
      "metric_definition": "a640e390-fa13-4bb0-b2cd-1e0cb3f43eb9",
      "values": [{ "LightColorR_PointLight5": 0.6442325,
                       "LightColorG_PointLight5": 0.2307689,
                       "LightColorB_PointLight5": 0.4284794,
                       "LightColorA_PointLight5": 1 }]
    },
    {
      "capture_id": null,
      "annotation_id": null,
      "sequence_id": "aaf0f9c2-6c84-47b1-8209-41c3bbd60d46",
      "step": 0,
      "metric_definition": "c0b5e272-9715-4ea2-930e-cfe8cecf1b6e",
      "values": [{ "LightPositionX_PointLight6": 0,
                       "LightPositionY_PointLight6": 0,
                       "LightPositionZ_PointLight6": -7 }]
    },
    {
      "capture_id": null,
      "annotation_id": null,
      "sequence_id": "aaf0f9c2-6c84-47b1-8209-41c3bbd60d46",
      "step": 0,
      "metric_definition": "317735b9-b4a4-4f6b-a4c9-eb846463a583",
      "values": [{ "LightRotationX_PointLight6": 90,
                       "LightRotationY_PointLight6": 89.99998,
                       "LightRotationZ_PointLight6": 0 }]
    },
    {
      "capture_id": null,
      "annotation_id": null,
      "sequence_id": "aaf0f9c2-6c84-47b1-8209-41c3bbd60d46",
      "step": 0,
      "metric_definition": "1a709e09-81bd-43b5-b8f0-f3952a1af444",
      "values": [{ "LightIntensity_PointLight6": 42580.93 }]
    },
    {
      "capture_id": null,
      "annotation_id": null,
      "sequence_id": "aaf0f9c2-6c84-47b1-8209-41c3bbd60d46",
      "step": 0,
      "metric_definition": "a640e390-fa13-4bb0-b2cd-1e0cb3f43eb9",
      "values": [{ "LightColorR_PointLight6": 0.6708373,
                       "LightColorG_PointLight6": 0.6563364,
                       "LightColorB_PointLight6": 0.2335486,
                       "LightColorA_PointLight6": 1 }]
    },
    {
      "capture_id": null,
      "annotation_id": null,
      "sequence_id": "aaf0f9c2-6c84-47b1-8209-41c3bbd60d46",
      "step": 0,
      "metric_definition": "c0b5e272-9715-4ea2-930e-cfe8cecf1b6e",
      "values": [{ "LightPositionX_PointLightSceneMoving": 0.319116,
                       "LightPositionY_PointLightSceneMoving": 10.26229,
                       "LightPositionZ_PointLightSceneMoving": 0.326005 }]
    },
    {
      "capture_id": null,
      "annotation_id": null,
      "sequence_id": "aaf0f9c2-6c84-47b1-8209-41c3bbd60d46",
      "step": 0,
      "metric_definition": "317735b9-b4a4-4f6b-a4c9-eb846463a583",
      "values": [{ "LightRotationX_PointLightSceneMoving": 315.4055,
                       "LightRotationY_PointLightSceneMoving": 324.7572,
                       "LightRotationZ_PointLightSceneMoving": 33.02114 }]
    },
    {
      "capture_id": null,
      "annotation_id": null,
      "sequence_id": "aaf0f9c2-6c84-47b1-8209-41c3bbd60d46",
      "step": 0,
      "metric_definition": "1a709e09-81bd-43b5-b8f0-f3952a1af444",
      "values": [{ "LightIntensity_PointLightSceneMoving": 11133.28 }]
    },
    {
      "capture_id": null,
      "annotation_id": null,
      "sequence_id": "aaf0f9c2-6c84-47b1-8209-41c3bbd60d46",
      "step": 0,
      "metric_definition": "a640e390-fa13-4bb0-b2cd-1e0cb3f43eb9",
      "values": [{ "LightColorR_PointLightSceneMoving": 0.5640315,
                       "LightColorG_PointLightSceneMoving": 0.7285701,
                       "LightColorB_PointLightSceneMoving": 0.9570444,
                       "LightColorA_PointLightSceneMoving": 1 }]
    },
    {
      "capture_id": null,
      "annotation_id": null,
      "sequence_id": "aaf0f9c2-6c84-47b1-8209-41c3bbd60d46",
      "step": 0,
      "metric_definition": "1529faeb-863f-40c2-840f-5fe4221c1065",
      "values": [{ "CameraPositionX": -4.109427, "CameraPositionY": 3.632261, "CameraPositionZ": 18.87753 }]
    },
    {
      "capture_id": null,
      "annotation_id": null,
      "sequence_id": "aaf0f9c2-6c84-47b1-8209-41c3bbd60d46",
      "step": 0,
      "metric_definition": "5199deef-2eb0-42fe-b00d-1d2418aedaff",
      "values": [{ "CameraRotationX": 359.6443, "CameraRotationY": 176.5489, "CameraRotationZ": 359.1425 }]
    },
    {
      "capture_id": null,
      "annotation_id": null,
      "sequence_id": "aaf0f9c2-6c84-47b1-8209-41c3bbd60d46",
      "step": 0,
      "metric_definition": "42e7fa88-084b-423d-ba6e-830c711383e1",
      "values": [{ "CameraFieldOfView": 41.70833 }]
    },
    {
      "capture_id": null,
      "annotation_id": null,
      "sequence_id": "aaf0f9c2-6c84-47b1-8209-41c3bbd60d46",
      "step": 0,
      "metric_definition": "11aa1dfc-3495-467c-a998-71d9bfe6980e",
      "values": [{ "CameraFocalLength": 9.937492 }]
    },
    {
      "capture_id": "7e592298-d9eb-4ad7-b581-311cba5518ef",
      "annotation_id": null,
      "sequence_id": "aaf0f9c2-6c84-47b1-8209-41c3bbd60d46",
      "step": 0,
      "metric_definition": "51da3c27-369d-4929-aea6-d01614635ce2",
      "values": [
        {
          "label_id": 1,
          "label_name": "person",
          "count": 11
        }
      ]
    },
    {
      "capture_id": "7e592298-d9eb-4ad7-b581-311cba5518ef",
      "annotation_id": null,
      "sequence_id": "aaf0f9c2-6c84-47b1-8209-41c3bbd60d46",
      "step": 0,
      "metric_definition": "5ba92024-b3b7-41a7-9d3f-c03a6a8ddd01",
      "values": [
        {
          "label_id": 1,
          "instance_id": 5,
          "instance_color": {
            "r": 0,
            "g": 255,
            "b": 212,
            "a": 255
          },
          "visible_pixels": 4463
        },
        {
          "label_id": 1,
          "instance_id": 8,
          "instance_color": {
            "r": 11,
            "g": 255,
            "b": 0,
            "a": 255
          },
          "visible_pixels": 1604
        },
        {
          "label_id": 1,
          "instance_id": 1,
          "instance_color": {
            "r": 255,
            "g": 0,
            "b": 0,
            "a": 255
          },
          "visible_pixels": 703
        },
        {
          "label_id": 1,
          "instance_id": 36,
          "instance_color": {
            "r": 0,
            "g": 54,
            "b": 255,
            "a": 255
          },
          "visible_pixels": 3706
        },
        {
          "label_id": 1,
          "instance_id": 2,
          "instance_color": {
            "r": 0,
            "g": 74,
            "b": 255,
            "a": 255
          },
          "visible_pixels": 4135
        },
        {
          "label_id": 1,
          "instance_id": 14,
          "instance_color": {
            "r": 255,
            "g": 53,
            "b": 0,
            "a": 255
          },
          "visible_pixels": 1210
        },
        {
          "label_id": 1,
          "instance_id": 46,
          "instance_color": {
            "r": 222,
            "g": 0,
            "b": 255,
            "a": 255
          },
          "visible_pixels": 16198
        },
        {
          "label_id": 1,
          "instance_id": 31,
          "instance_color": {
            "r": 0,
            "g": 192,
            "b": 255,
            "a": 255
          },
          "visible_pixels": 4071
        },
        {
          "label_id": 1,
          "instance_id": 17,
          "instance_color": {
            "r": 255,
            "g": 0,
            "b": 171,
            "a": 255
          },
          "visible_pixels": 84
        },
        {
          "label_id": 1,
          "instance_id": 3,
          "instance_color": {
            "r": 149,
            "g": 255,
            "b": 0,
            "a": 255
          },
          "visible_pixels": 2717
        },
        {
          "label_id": 1,
          "instance_id": 22,
          "instance_color": {
            "r": 255,
            "g": 0,
            "b": 33,
            "a": 255
          },
          "visible_pixels": 902
        }
      ]
    },
    {
      "capture_id": null,
      "annotation_id": null,
      "sequence_id": "c5dedbdc-47ec-42bf-b925-88f039076e6d",
      "step": 0,
      "metric_definition": "db1b258e-d1d0-41b6-8751-16f601a2e230",
      "values": [
        {
          "iteration": 34
        }
      ]
    },
    {
      "capture_id": null,
      "annotation_id": null,
      "sequence_id": "c5dedbdc-47ec-42bf-b925-88f039076e6d",
      "step": 0,
      "metric_definition": "c0b5e272-9715-4ea2-930e-cfe8cecf1b6e",
      "values": [{ "LightPositionX_DirectionalLightSun": 0,
                       "LightPositionY_DirectionalLightSun": 22,
                       "LightPositionZ_DirectionalLightSun": 14 }]
    },
    {
      "capture_id": null,
      "annotation_id": null,
      "sequence_id": "c5dedbdc-47ec-42bf-b925-88f039076e6d",
      "step": 0,
      "metric_definition": "317735b9-b4a4-4f6b-a4c9-eb846463a583",
      "values": [{ "LightRotationX_DirectionalLightSun": 343.3531,
                       "LightRotationY_DirectionalLightSun": 90.69819,
                       "LightRotationZ_DirectionalLightSun": 73.66716 }]
    },
    {
      "capture_id": null,
      "annotation_id": null,
      "sequence_id": "c5dedbdc-47ec-42bf-b925-88f039076e6d",
      "step": 0,
      "metric_definition": "1a709e09-81bd-43b5-b8f0-f3952a1af444",
      "values": [{ "LightIntensity_DirectionalLightSun": 10000 }]
    },
    {
      "capture_id": null,
      "annotation_id": null,
      "sequence_id": "c5dedbdc-47ec-42bf-b925-88f039076e6d",
      "step": 0,
      "metric_definition": "a640e390-fa13-4bb0-b2cd-1e0cb3f43eb9",
      "values": [{ "LightColorR_DirectionalLightSun": 1,
                       "LightColorG_DirectionalLightSun": 0.9568627,
                       "LightColorB_DirectionalLightSun": 0.8392157,
                       "LightColorA_DirectionalLightSun": 1 }]
    },
    {
      "capture_id": null,
      "annotation_id": null,
      "sequence_id": "c5dedbdc-47ec-42bf-b925-88f039076e6d",
      "step": 0,
      "metric_definition": "c0b5e272-9715-4ea2-930e-cfe8cecf1b6e",
      "values": [{ "LightPositionX_PointLight1": -10,
                       "LightPositionY_PointLight1": 0,
                       "LightPositionZ_PointLight1": 0 }]
    },
    {
      "capture_id": null,
      "annotation_id": null,
      "sequence_id": "c5dedbdc-47ec-42bf-b925-88f039076e6d",
      "step": 0,
      "metric_definition": "317735b9-b4a4-4f6b-a4c9-eb846463a583",
      "values": [{ "LightRotationX_PointLight1": 0,
                       "LightRotationY_PointLight1": 0,
                       "LightRotationZ_PointLight1": 0 }]
    },
    {
      "capture_id": null,
      "annotation_id": null,
      "sequence_id": "c5dedbdc-47ec-42bf-b925-88f039076e6d",
      "step": 0,
      "metric_definition": "1a709e09-81bd-43b5-b8f0-f3952a1af444",
      "values": [{ "LightIntensity_PointLight1": 39786.8 }]
    },
    {
      "capture_id": null,
      "annotation_id": null,
      "sequence_id": "c5dedbdc-47ec-42bf-b925-88f039076e6d",
      "step": 0,
      "metric_definition": "a640e390-fa13-4bb0-b2cd-1e0cb3f43eb9",
      "values": [{ "LightColorR_PointLight1": 0.8855692,
                       "LightColorG_PointLight1": 0.7261274,
                       "LightColorB_PointLight1": 0.2351804,
                       "LightColorA_PointLight1": 1 }]
    },
    {
      "capture_id": null,
      "annotation_id": null,
      "sequence_id": "c5dedbdc-47ec-42bf-b925-88f039076e6d",
      "step": 0,
      "metric_definition": "c0b5e272-9715-4ea2-930e-cfe8cecf1b6e",
      "values": [{ "LightPositionX_PointLight2": 10,
                       "LightPositionY_PointLight2": 0,
                       "LightPositionZ_PointLight2": 0 }]
    },
    {
      "capture_id": null,
      "annotation_id": null,
      "sequence_id": "c5dedbdc-47ec-42bf-b925-88f039076e6d",
      "step": 0,
      "metric_definition": "317735b9-b4a4-4f6b-a4c9-eb846463a583",
      "values": [{ "LightRotationX_PointLight2": 0,
                       "LightRotationY_PointLight2": 0,
                       "LightRotationZ_PointLight2": 0 }]
    },
    {
      "capture_id": null,
      "annotation_id": null,
      "sequence_id": "c5dedbdc-47ec-42bf-b925-88f039076e6d",
      "step": 0,
      "metric_definition": "1a709e09-81bd-43b5-b8f0-f3952a1af444",
      "values": [{ "LightIntensity_PointLight2": 24491.11 }]
    },
    {
      "capture_id": null,
      "annotation_id": null,
      "sequence_id": "c5dedbdc-47ec-42bf-b925-88f039076e6d",
      "step": 0,
      "metric_definition": "a640e390-fa13-4bb0-b2cd-1e0cb3f43eb9",
      "values": [{ "LightColorR_PointLight2": 0.633509,
                       "LightColorG_PointLight2": 0.3195662,
                       "LightColorB_PointLight2": 0.9361398,
                       "LightColorA_PointLight2": 1 }]
    },
    {
      "capture_id": null,
      "annotation_id": null,
      "sequence_id": "c5dedbdc-47ec-42bf-b925-88f039076e6d",
      "step": 0,
      "metric_definition": "c0b5e272-9715-4ea2-930e-cfe8cecf1b6e",
      "values": [{ "LightPositionX_PointLight3": 0,
                       "LightPositionY_PointLight3": 10,
                       "LightPositionZ_PointLight3": 0 }]
    },
    {
      "capture_id": null,
      "annotation_id": null,
      "sequence_id": "c5dedbdc-47ec-42bf-b925-88f039076e6d",
      "step": 0,
      "metric_definition": "317735b9-b4a4-4f6b-a4c9-eb846463a583",
      "values": [{ "LightRotationX_PointLight3": 0,
                       "LightRotationY_PointLight3": 0,
                       "LightRotationZ_PointLight3": 270 }]
    },
    {
      "capture_id": null,
      "annotation_id": null,
      "sequence_id": "c5dedbdc-47ec-42bf-b925-88f039076e6d",
      "step": 0,
      "metric_definition": "1a709e09-81bd-43b5-b8f0-f3952a1af444",
      "values": [{ "LightIntensity_PointLight3": 21288.14 }]
    },
    {
      "capture_id": null,
      "annotation_id": null,
      "sequence_id": "c5dedbdc-47ec-42bf-b925-88f039076e6d",
      "step": 0,
      "metric_definition": "a640e390-fa13-4bb0-b2cd-1e0cb3f43eb9",
      "values": [{ "LightColorR_PointLight3": 0.2734766,
                       "LightColorG_PointLight3": 0.03523219,
                       "LightColorB_PointLight3": 0.7485455,
                       "LightColorA_PointLight3": 1 }]
    },
    {
      "capture_id": null,
      "annotation_id": null,
      "sequence_id": "c5dedbdc-47ec-42bf-b925-88f039076e6d",
      "step": 0,
      "metric_definition": "c0b5e272-9715-4ea2-930e-cfe8cecf1b6e",
      "values": [{ "LightPositionX_PointLight4": 0,
                       "LightPositionY_PointLight4": -11,
                       "LightPositionZ_PointLight4": 0 }]
    },
    {
      "capture_id": null,
      "annotation_id": null,
      "sequence_id": "c5dedbdc-47ec-42bf-b925-88f039076e6d",
      "step": 0,
      "metric_definition": "317735b9-b4a4-4f6b-a4c9-eb846463a583",
      "values": [{ "LightRotationX_PointLight4": 0,
                       "LightRotationY_PointLight4": 0,
                       "LightRotationZ_PointLight4": 270 }]
    },
    {
      "capture_id": null,
      "annotation_id": null,
      "sequence_id": "c5dedbdc-47ec-42bf-b925-88f039076e6d",
      "step": 0,
      "metric_definition": "1a709e09-81bd-43b5-b8f0-f3952a1af444",
      "values": [{ "LightIntensity_PointLight4": 11040.33 }]
    },
    {
      "capture_id": null,
      "annotation_id": null,
      "sequence_id": "c5dedbdc-47ec-42bf-b925-88f039076e6d",
      "step": 0,
      "metric_definition": "a640e390-fa13-4bb0-b2cd-1e0cb3f43eb9",
      "values": [{ "LightColorR_PointLight4": 0.6144599,
                       "LightColorG_PointLight4": 0.337563,
                       "LightColorB_PointLight4": 0.06917357,
                       "LightColorA_PointLight4": 1 }]
    },
    {
      "capture_id": null,
      "annotation_id": null,
      "sequence_id": "c5dedbdc-47ec-42bf-b925-88f039076e6d",
      "step": 0,
      "metric_definition": "c0b5e272-9715-4ea2-930e-cfe8cecf1b6e",
      "values": [{ "LightPositionX_PointLight5": 0,
                       "LightPositionY_PointLight5": 0,
                       "LightPositionZ_PointLight5": 10 }]
    },
    {
      "capture_id": null,
      "annotation_id": null,
      "sequence_id": "c5dedbdc-47ec-42bf-b925-88f039076e6d",
      "step": 0,
      "metric_definition": "317735b9-b4a4-4f6b-a4c9-eb846463a583",
      "values": [{ "LightRotationX_PointLight5": 90,
                       "LightRotationY_PointLight5": 89.99998,
                       "LightRotationZ_PointLight5": 0 }]
    },
    {
      "capture_id": null,
      "annotation_id": null,
      "sequence_id": "c5dedbdc-47ec-42bf-b925-88f039076e6d",
      "step": 0,
      "metric_definition": "1a709e09-81bd-43b5-b8f0-f3952a1af444",
      "values": [{ "LightIntensity_PointLight5": 8635.648 }]
    },
    {
      "capture_id": null,
      "annotation_id": null,
      "sequence_id": "c5dedbdc-47ec-42bf-b925-88f039076e6d",
      "step": 0,
      "metric_definition": "a640e390-fa13-4bb0-b2cd-1e0cb3f43eb9",
      "values": [{ "LightColorR_PointLight5": 0.6374096,
                       "LightColorG_PointLight5": 0.8176028,
                       "LightColorB_PointLight5": 0.765292,
                       "LightColorA_PointLight5": 1 }]
    },
    {
      "capture_id": null,
      "annotation_id": null,
      "sequence_id": "c5dedbdc-47ec-42bf-b925-88f039076e6d",
      "step": 0,
      "metric_definition": "c0b5e272-9715-4ea2-930e-cfe8cecf1b6e",
      "values": [{ "LightPositionX_PointLight6": 0,
                       "LightPositionY_PointLight6": 0,
                       "LightPositionZ_PointLight6": -7 }]
    },
    {
      "capture_id": null,
      "annotation_id": null,
      "sequence_id": "c5dedbdc-47ec-42bf-b925-88f039076e6d",
      "step": 0,
      "metric_definition": "317735b9-b4a4-4f6b-a4c9-eb846463a583",
      "values": [{ "LightRotationX_PointLight6": 90,
                       "LightRotationY_PointLight6": 89.99998,
                       "LightRotationZ_PointLight6": 0 }]
    },
    {
      "capture_id": null,
      "annotation_id": null,
      "sequence_id": "c5dedbdc-47ec-42bf-b925-88f039076e6d",
      "step": 0,
      "metric_definition": "1a709e09-81bd-43b5-b8f0-f3952a1af444",
      "values": [{ "LightIntensity_PointLight6": 27478.25 }]
    },
    {
      "capture_id": null,
      "annotation_id": null,
      "sequence_id": "c5dedbdc-47ec-42bf-b925-88f039076e6d",
      "step": 0,
      "metric_definition": "a640e390-fa13-4bb0-b2cd-1e0cb3f43eb9",
      "values": [{ "LightColorR_PointLight6": 0.3439004,
                       "LightColorG_PointLight6": 0.383821,
                       "LightColorB_PointLight6": 0.4739501,
                       "LightColorA_PointLight6": 1 }]
    },
    {
      "capture_id": null,
      "annotation_id": null,
      "sequence_id": "c5dedbdc-47ec-42bf-b925-88f039076e6d",
      "step": 0,
      "metric_definition": "c0b5e272-9715-4ea2-930e-cfe8cecf1b6e",
      "values": [{ "LightPositionX_PointLightSceneMoving": 3.359969,
                       "LightPositionY_PointLightSceneMoving": 5.914294,
                       "LightPositionZ_PointLightSceneMoving": -0.8742089 }]
    },
    {
      "capture_id": null,
      "annotation_id": null,
      "sequence_id": "c5dedbdc-47ec-42bf-b925-88f039076e6d",
      "step": 0,
      "metric_definition": "317735b9-b4a4-4f6b-a4c9-eb846463a583",
      "values": [{ "LightRotationX_PointLightSceneMoving": 4.836643,
                       "LightRotationY_PointLightSceneMoving": 26.46932,
                       "LightRotationZ_PointLightSceneMoving": 357.6955 }]
    },
    {
      "capture_id": null,
      "annotation_id": null,
      "sequence_id": "c5dedbdc-47ec-42bf-b925-88f039076e6d",
      "step": 0,
      "metric_definition": "1a709e09-81bd-43b5-b8f0-f3952a1af444",
      "values": [{ "LightIntensity_PointLightSceneMoving": 14113.33 }]
    },
    {
      "capture_id": null,
      "annotation_id": null,
      "sequence_id": "c5dedbdc-47ec-42bf-b925-88f039076e6d",
      "step": 0,
      "metric_definition": "a640e390-fa13-4bb0-b2cd-1e0cb3f43eb9",
      "values": [{ "LightColorR_PointLightSceneMoving": 0.6687586,
                       "LightColorG_PointLightSceneMoving": 0.9039123,
                       "LightColorB_PointLightSceneMoving": 0.7806619,
                       "LightColorA_PointLightSceneMoving": 1 }]
    },
    {
      "capture_id": null,
      "annotation_id": null,
      "sequence_id": "c5dedbdc-47ec-42bf-b925-88f039076e6d",
      "step": 0,
      "metric_definition": "1529faeb-863f-40c2-840f-5fe4221c1065",
      "values": [{ "CameraPositionX": -2.934494, "CameraPositionY": -4.296572, "CameraPositionZ": 17.51537 }]
    },
    {
      "capture_id": null,
      "annotation_id": null,
      "sequence_id": "c5dedbdc-47ec-42bf-b925-88f039076e6d",
      "step": 0,
      "metric_definition": "5199deef-2eb0-42fe-b00d-1d2418aedaff",
      "values": [{ "CameraRotationX": 358.3592, "CameraRotationY": 176.533, "CameraRotationZ": 358.5178 }]
    },
    {
      "capture_id": null,
      "annotation_id": null,
      "sequence_id": "c5dedbdc-47ec-42bf-b925-88f039076e6d",
      "step": 0,
      "metric_definition": "42e7fa88-084b-423d-ba6e-830c711383e1",
      "values": [{ "CameraFieldOfView": 5.295075 }]
    },
    {
      "capture_id": null,
      "annotation_id": null,
      "sequence_id": "c5dedbdc-47ec-42bf-b925-88f039076e6d",
      "step": 0,
      "metric_definition": "11aa1dfc-3495-467c-a998-71d9bfe6980e",
      "values": [{ "CameraFocalLength": 7.311528 }]
    }
  ]
}