{
  "version": "0.0.1",
  "metrics": [
    {
      "capture_id": "e7c59abf-d096-48c1-9a5e-92f397c01d0b",
      "annotation_id": null,
      "sequence_id": "5e6c05fb-ef69-4573-8933-2fe43e41883f",
      "step": 0,
      "metric_definition": "51da3c27-369d-4929-aea6-d01614635ce2",
      "values": [
        {
          "label_id": 1,
          "label_name": "person",
          "count": 1
        }
      ]
    },
    {
      "capture_id": "e7c59abf-d096-48c1-9a5e-92f397c01d0b",
      "annotation_id": null,
      "sequence_id": "5e6c05fb-ef69-4573-8933-2fe43e41883f",
      "step": 0,
      "metric_definition": "5ba92024-b3b7-41a7-9d3f-c03a6a8ddd01",
      "values": [
        {
          "label_id": 1,
          "instance_id": 2,
          "instance_color": {
            "r": 0,
            "g": 74,
            "b": 255,
            "a": 255
          },
          "visible_pixels": 16905
        }
      ]
    },
    {
      "capture_id": null,
      "annotation_id": null,
      "sequence_id": "6281e98e-cec7-49cb-8b4c-1e08b5c0a089",
      "step": 0,
      "metric_definition": "db1b258e-d1d0-41b6-8751-16f601a2e230",
      "values": [
        {
          "iteration": 7
        }
      ]
    },
    {
      "capture_id": null,
      "annotation_id": null,
      "sequence_id": "6281e98e-cec7-49cb-8b4c-1e08b5c0a089",
      "step": 0,
      "metric_definition": "c0b5e272-9715-4ea2-930e-cfe8cecf1b6e",
      "values": [{ "LightPositionX_DirectionalLightSun": 0,
                       "LightPositionY_DirectionalLightSun": 22,
                       "LightPositionZ_DirectionalLightSun": 14 }]
    },
    {
      "capture_id": null,
      "annotation_id": null,
      "sequence_id": "6281e98e-cec7-49cb-8b4c-1e08b5c0a089",
      "step": 0,
      "metric_definition": "317735b9-b4a4-4f6b-a4c9-eb846463a583",
      "values": [{ "LightRotationX_DirectionalLightSun": 29.89538,
                       "LightRotationY_DirectionalLightSun": 265.7385,
                       "LightRotationZ_DirectionalLightSun": 278.3138 }]
    },
    {
      "capture_id": null,
      "annotation_id": null,
      "sequence_id": "6281e98e-cec7-49cb-8b4c-1e08b5c0a089",
      "step": 0,
      "metric_definition": "1a709e09-81bd-43b5-b8f0-f3952a1af444",
      "values": [{ "LightIntensity_DirectionalLightSun": 10000 }]
    },
    {
      "capture_id": null,
      "annotation_id": null,
      "sequence_id": "6281e98e-cec7-49cb-8b4c-1e08b5c0a089",
      "step": 0,
      "metric_definition": "a640e390-fa13-4bb0-b2cd-1e0cb3f43eb9",
      "values": [{ "LightColorR_DirectionalLightSun": 1,
                       "LightColorG_DirectionalLightSun": 0.9568627,
                       "LightColorB_DirectionalLightSun": 0.8392157,
                       "LightColorA_DirectionalLightSun": 1 }]
    },
    {
      "capture_id": null,
      "annotation_id": null,
      "sequence_id": "6281e98e-cec7-49cb-8b4c-1e08b5c0a089",
      "step": 0,
      "metric_definition": "c0b5e272-9715-4ea2-930e-cfe8cecf1b6e",
      "values": [{ "LightPositionX_PointLight1": -10,
                       "LightPositionY_PointLight1": 0,
                       "LightPositionZ_PointLight1": 0 }]
    },
    {
      "capture_id": null,
      "annotation_id": null,
      "sequence_id": "6281e98e-cec7-49cb-8b4c-1e08b5c0a089",
      "step": 0,
      "metric_definition": "317735b9-b4a4-4f6b-a4c9-eb846463a583",
      "values": [{ "LightRotationX_PointLight1": 0,
                       "LightRotationY_PointLight1": 0,
                       "LightRotationZ_PointLight1": 0 }]
    },
    {
      "capture_id": null,
      "annotation_id": null,
      "sequence_id": "6281e98e-cec7-49cb-8b4c-1e08b5c0a089",
      "step": 0,
      "metric_definition": "1a709e09-81bd-43b5-b8f0-f3952a1af444",
      "values": [{ "LightIntensity_PointLight1": 20426.66 }]
    },
    {
      "capture_id": null,
      "annotation_id": null,
      "sequence_id": "6281e98e-cec7-49cb-8b4c-1e08b5c0a089",
      "step": 0,
      "metric_definition": "a640e390-fa13-4bb0-b2cd-1e0cb3f43eb9",
      "values": [{ "LightColorR_PointLight1": 0.7560282,
                       "LightColorG_PointLight1": 0.2040809,
                       "LightColorB_PointLight1": 0.3371397,
                       "LightColorA_PointLight1": 1 }]
    },
    {
      "capture_id": null,
      "annotation_id": null,
      "sequence_id": "6281e98e-cec7-49cb-8b4c-1e08b5c0a089",
      "step": 0,
      "metric_definition": "c0b5e272-9715-4ea2-930e-cfe8cecf1b6e",
      "values": [{ "LightPositionX_PointLight2": 10,
                       "LightPositionY_PointLight2": 0,
                       "LightPositionZ_PointLight2": 0 }]
    },
    {
      "capture_id": null,
      "annotation_id": null,
      "sequence_id": "6281e98e-cec7-49cb-8b4c-1e08b5c0a089",
      "step": 0,
      "metric_definition": "317735b9-b4a4-4f6b-a4c9-eb846463a583",
      "values": [{ "LightRotationX_PointLight2": 0,
                       "LightRotationY_PointLight2": 0,
                       "LightRotationZ_PointLight2": 0 }]
    },
    {
      "capture_id": null,
      "annotation_id": null,
      "sequence_id": "6281e98e-cec7-49cb-8b4c-1e08b5c0a089",
      "step": 0,
      "metric_definition": "1a709e09-81bd-43b5-b8f0-f3952a1af444",
      "values": [{ "LightIntensity_PointLight2": 20116.41 }]
    },
    {
      "capture_id": null,
      "annotation_id": null,
      "sequence_id": "6281e98e-cec7-49cb-8b4c-1e08b5c0a089",
      "step": 0,
      "metric_definition": "a640e390-fa13-4bb0-b2cd-1e0cb3f43eb9",
      "values": [{ "LightColorR_PointLight2": 0.6429696,
                       "LightColorG_PointLight2": 0.8407185,
                       "LightColorB_PointLight2": 0.3712574,
                       "LightColorA_PointLight2": 1 }]
    },
    {
      "capture_id": null,
      "annotation_id": null,
      "sequence_id": "6281e98e-cec7-49cb-8b4c-1e08b5c0a089",
      "step": 0,
      "metric_definition": "c0b5e272-9715-4ea2-930e-cfe8cecf1b6e",
      "values": [{ "LightPositionX_PointLight3": 0,
                       "LightPositionY_PointLight3": 10,
                       "LightPositionZ_PointLight3": 0 }]
    },
    {
      "capture_id": null,
      "annotation_id": null,
      "sequence_id": "6281e98e-cec7-49cb-8b4c-1e08b5c0a089",
      "step": 0,
      "metric_definition": "317735b9-b4a4-4f6b-a4c9-eb846463a583",
      "values": [{ "LightRotationX_PointLight3": 0,
                       "LightRotationY_PointLight3": 0,
                       "LightRotationZ_PointLight3": 270 }]
    },
    {
      "capture_id": null,
      "annotation_id": null,
      "sequence_id": "6281e98e-cec7-49cb-8b4c-1e08b5c0a089",
      "step": 0,
      "metric_definition": "1a709e09-81bd-43b5-b8f0-f3952a1af444",
      "values": [{ "LightIntensity_PointLight3": 7577.753 }]
    },
    {
      "capture_id": null,
      "annotation_id": null,
      "sequence_id": "6281e98e-cec7-49cb-8b4c-1e08b5c0a089",
      "step": 0,
      "metric_definition": "a640e390-fa13-4bb0-b2cd-1e0cb3f43eb9",
      "values": [{ "LightColorR_PointLight3": 0.7149169,
                       "LightColorG_PointLight3": 0.1254264,
                       "LightColorB_PointLight3": 0.3709304,
                       "LightColorA_PointLight3": 1 }]
    },
    {
      "capture_id": null,
      "annotation_id": null,
      "sequence_id": "6281e98e-cec7-49cb-8b4c-1e08b5c0a089",
      "step": 0,
      "metric_definition": "c0b5e272-9715-4ea2-930e-cfe8cecf1b6e",
      "values": [{ "LightPositionX_PointLight4": 0,
                       "LightPositionY_PointLight4": -11,
                       "LightPositionZ_PointLight4": 0 }]
    },
    {
      "capture_id": null,
      "annotation_id": null,
      "sequence_id": "6281e98e-cec7-49cb-8b4c-1e08b5c0a089",
      "step": 0,
      "metric_definition": "317735b9-b4a4-4f6b-a4c9-eb846463a583",
      "values": [{ "LightRotationX_PointLight4": 0,
                       "LightRotationY_PointLight4": 0,
                       "LightRotationZ_PointLight4": 270 }]
    },
    {
      "capture_id": null,
      "annotation_id": null,
      "sequence_id": "6281e98e-cec7-49cb-8b4c-1e08b5c0a089",
      "step": 0,
      "metric_definition": "1a709e09-81bd-43b5-b8f0-f3952a1af444",
      "values": [{ "LightIntensity_PointLight4": 23250.08 }]
    },
    {
      "capture_id": null,
      "annotation_id": null,
      "sequence_id": "6281e98e-cec7-49cb-8b4c-1e08b5c0a089",
      "step": 0,
      "metric_definition": "a640e390-fa13-4bb0-b2cd-1e0cb3f43eb9",
      "values": [{ "LightColorR_PointLight4": 0.7919986,
                       "LightColorG_PointLight4": 0.01219153,
                       "LightColorB_PointLight4": 0.3857354,
                       "LightColorA_PointLight4": 1 }]
    },
    {
      "capture_id": null,
      "annotation_id": null,
      "sequence_id": "6281e98e-cec7-49cb-8b4c-1e08b5c0a089",
      "step": 0,
      "metric_definition": "c0b5e272-9715-4ea2-930e-cfe8cecf1b6e",
      "values": [{ "LightPositionX_PointLight5": 0,
                       "LightPositionY_PointLight5": 0,
                       "LightPositionZ_PointLight5": 10 }]
    },
    {
      "capture_id": null,
      "annotation_id": null,
      "sequence_id": "6281e98e-cec7-49cb-8b4c-1e08b5c0a089",
      "step": 0,
      "metric_definition": "317735b9-b4a4-4f6b-a4c9-eb846463a583",
      "values": [{ "LightRotationX_PointLight5": 90,
                       "LightRotationY_PointLight5": 89.99998,
                       "LightRotationZ_PointLight5": 0 }]
    },
    {
      "capture_id": null,
      "annotation_id": null,
      "sequence_id": "6281e98e-cec7-49cb-8b4c-1e08b5c0a089",
      "step": 0,
      "metric_definition": "1a709e09-81bd-43b5-b8f0-f3952a1af444",
      "values": [{ "LightIntensity_PointLight5": 18137.13 }]
    },
    {
      "capture_id": null,
      "annotation_id": null,
      "sequence_id": "6281e98e-cec7-49cb-8b4c-1e08b5c0a089",
      "step": 0,
      "metric_definition": "a640e390-fa13-4bb0-b2cd-1e0cb3f43eb9",
      "values": [{ "LightColorR_PointLight5": 0.09726608,
                       "LightColorG_PointLight5": 0.1825081,
                       "LightColorB_PointLight5": 0.816663,
                       "LightColorA_PointLight5": 1 }]
    },
    {
      "capture_id": null,
      "annotation_id": null,
      "sequence_id": "6281e98e-cec7-49cb-8b4c-1e08b5c0a089",
      "step": 0,
      "metric_definition": "c0b5e272-9715-4ea2-930e-cfe8cecf1b6e",
      "values": [{ "LightPositionX_PointLight6": 0,
                       "LightPositionY_PointLight6": 0,
                       "LightPositionZ_PointLight6": -7 }]
    },
    {
      "capture_id": null,
      "annotation_id": null,
      "sequence_id": "6281e98e-cec7-49cb-8b4c-1e08b5c0a089",
      "step": 0,
      "metric_definition": "317735b9-b4a4-4f6b-a4c9-eb846463a583",
      "values": [{ "LightRotationX_PointLight6": 90,
                       "LightRotationY_PointLight6": 89.99998,
                       "LightRotationZ_PointLight6": 0 }]
    },
    {
      "capture_id": null,
      "annotation_id": null,
      "sequence_id": "6281e98e-cec7-49cb-8b4c-1e08b5c0a089",
      "step": 0,
      "metric_definition": "1a709e09-81bd-43b5-b8f0-f3952a1af444",
      "values": [{ "LightIntensity_PointLight6": 18886.33 }]
    },
    {
      "capture_id": null,
      "annotation_id": null,
      "sequence_id": "6281e98e-cec7-49cb-8b4c-1e08b5c0a089",
      "step": 0,
      "metric_definition": "a640e390-fa13-4bb0-b2cd-1e0cb3f43eb9",
      "values": [{ "LightColorR_PointLight6": 0.3157696,
                       "LightColorG_PointLight6": 0.2979931,
                       "LightColorB_PointLight6": 0.579239,
                       "LightColorA_PointLight6": 1 }]
    },
    {
      "capture_id": null,
      "annotation_id": null,
      "sequence_id": "6281e98e-cec7-49cb-8b4c-1e08b5c0a089",
      "step": 0,
      "metric_definition": "c0b5e272-9715-4ea2-930e-cfe8cecf1b6e",
      "values": [{ "LightPositionX_PointLightSceneMoving": -0.9689273,
                       "LightPositionY_PointLightSceneMoving": 4.296965,
                       "LightPositionZ_PointLightSceneMoving": 4.951266 }]
    },
    {
      "capture_id": null,
      "annotation_id": null,
      "sequence_id": "6281e98e-cec7-49cb-8b4c-1e08b5c0a089",
      "step": 0,
      "metric_definition": "317735b9-b4a4-4f6b-a4c9-eb846463a583",
      "values": [{ "LightRotationX_PointLightSceneMoving": 315.0984,
                       "LightRotationY_PointLightSceneMoving": 20.12265,
                       "LightRotationZ_PointLightSceneMoving": 341.8725 }]
    },
    {
      "capture_id": null,
      "annotation_id": null,
      "sequence_id": "6281e98e-cec7-49cb-8b4c-1e08b5c0a089",
      "step": 0,
      "metric_definition": "1a709e09-81bd-43b5-b8f0-f3952a1af444",
      "values": [{ "LightIntensity_PointLightSceneMoving": 22911.62 }]
    },
    {
      "capture_id": null,
      "annotation_id": null,
      "sequence_id": "6281e98e-cec7-49cb-8b4c-1e08b5c0a089",
      "step": 0,
      "metric_definition": "a640e390-fa13-4bb0-b2cd-1e0cb3f43eb9",
      "values": [{ "LightColorR_PointLightSceneMoving": 0.6258441,
                       "LightColorG_PointLightSceneMoving": 0.2615178,
                       "LightColorB_PointLightSceneMoving": 0.4470654,
                       "LightColorA_PointLightSceneMoving": 1 }]
    },
    {
      "capture_id": null,
      "annotation_id": null,
      "sequence_id": "6281e98e-cec7-49cb-8b4c-1e08b5c0a089",
      "step": 0,
      "metric_definition": "1529faeb-863f-40c2-840f-5fe4221c1065",
      "values": [{ "CameraPositionX": 2.72386, "CameraPositionY": 4.649659, "CameraPositionZ": 17.08951 }]
    },
    {
      "capture_id": null,
      "annotation_id": null,
      "sequence_id": "6281e98e-cec7-49cb-8b4c-1e08b5c0a089",
      "step": 0,
      "metric_definition": "5199deef-2eb0-42fe-b00d-1d2418aedaff",
      "values": [{ "CameraRotationX": 3.926851, "CameraRotationY": 182.0082, "CameraRotationZ": 358.0981 }]
    },
    {
      "capture_id": null,
      "annotation_id": null,
      "sequence_id": "6281e98e-cec7-49cb-8b4c-1e08b5c0a089",
      "step": 0,
      "metric_definition": "42e7fa88-084b-423d-ba6e-830c711383e1",
      "values": [{ "CameraFieldOfView": 27.32012 }]
    },
    {
      "capture_id": null,
      "annotation_id": null,
      "sequence_id": "6281e98e-cec7-49cb-8b4c-1e08b5c0a089",
      "step": 0,
      "metric_definition": "11aa1dfc-3495-467c-a998-71d9bfe6980e",
      "values": [{ "CameraFocalLength": 8.103457 }]
    },
    {
      "capture_id": "4f233ceb-9a17-4699-9804-c3ddedd547db",
      "annotation_id": null,
      "sequence_id": "6281e98e-cec7-49cb-8b4c-1e08b5c0a089",
      "step": 0,
      "metric_definition": "51da3c27-369d-4929-aea6-d01614635ce2",
      "values": [
        {
          "label_id": 1,
          "label_name": "person",
          "count": 6
        }
      ]
    },
    {
      "capture_id": "4f233ceb-9a17-4699-9804-c3ddedd547db",
      "annotation_id": null,
      "sequence_id": "6281e98e-cec7-49cb-8b4c-1e08b5c0a089",
      "step": 0,
      "metric_definition": "5ba92024-b3b7-41a7-9d3f-c03a6a8ddd01",
      "values": [
        {
          "label_id": 1,
          "instance_id": 5,
          "instance_color": {
            "r": 0,
            "g": 255,
            "b": 212,
            "a": 255
          },
          "visible_pixels": 598
        },
        {
          "label_id": 1,
          "instance_id": 43,
          "instance_color": {
            "r": 255,
            "g": 0,
            "b": 65,
            "a": 255
          },
          "visible_pixels": 3674
        },
        {
          "label_id": 1,
          "instance_id": 49,
          "instance_color": {
            "r": 0,
            "g": 2,
            "b": 255,
            "a": 255
          },
          "visible_pixels": 1756
        },
        {
          "label_id": 1,
          "instance_id": 2,
          "instance_color": {
            "r": 0,
            "g": 74,
            "b": 255,
            "a": 255
          },
          "visible_pixels": 4196
        },
        {
          "label_id": 1,
          "instance_id": 26,
          "instance_color": {
            "r": 0,
            "g": 255,
            "b": 180,
            "a": 255
          },
          "visible_pixels": 2938
        },
        {
          "label_id": 1,
          "instance_id": 29,
          "instance_color": {
            "r": 43,
            "g": 255,
            "b": 0,
            "a": 255
          },
          "visible_pixels": 4045
        }
      ]
    },
    {
      "capture_id": null,
      "annotation_id": null,
      "sequence_id": "405922af-9645-4f2a-a9b9-9cc70e5049f3",
      "step": 0,
      "metric_definition": "db1b258e-d1d0-41b6-8751-16f601a2e230",
      "values": [
        {
          "iteration": 8
        }
      ]
    },
    {
      "capture_id": null,
      "annotation_id": null,
      "sequence_id": "405922af-9645-4f2a-a9b9-9cc70e5049f3",
      "step": 0,
      "metric_definition": "c0b5e272-9715-4ea2-930e-cfe8cecf1b6e",
      "values": [{ "LightPositionX_DirectionalLightSun": 0,
                       "LightPositionY_DirectionalLightSun": 22,
                       "LightPositionZ_DirectionalLightSun": 14 }]
    },
    {
      "capture_id": null,
      "annotation_id": null,
      "sequence_id": "405922af-9645-4f2a-a9b9-9cc70e5049f3",
      "step": 0,
      "metric_definition": "317735b9-b4a4-4f6b-a4c9-eb846463a583",
      "values": [{ "LightRotationX_DirectionalLightSun": 71.02231,
                       "LightRotationY_DirectionalLightSun": 11.47257,
                       "LightRotationZ_DirectionalLightSun": 354.7333 }]
    },
    {
      "capture_id": null,
      "annotation_id": null,
      "sequence_id": "405922af-9645-4f2a-a9b9-9cc70e5049f3",
      "step": 0,
      "metric_definition": "1a709e09-81bd-43b5-b8f0-f3952a1af444",
      "values": [{ "LightIntensity_DirectionalLightSun": 10000 }]
    },
    {
      "capture_id": null,
      "annotation_id": null,
      "sequence_id": "405922af-9645-4f2a-a9b9-9cc70e5049f3",
      "step": 0,
      "metric_definition": "a640e390-fa13-4bb0-b2cd-1e0cb3f43eb9",
      "values": [{ "LightColorR_DirectionalLightSun": 1,
                       "LightColorG_DirectionalLightSun": 0.9568627,
                       "LightColorB_DirectionalLightSun": 0.8392157,
                       "LightColorA_DirectionalLightSun": 1 }]
    },
    {
      "capture_id": null,
      "annotation_id": null,
      "sequence_id": "405922af-9645-4f2a-a9b9-9cc70e5049f3",
      "step": 0,
      "metric_definition": "c0b5e272-9715-4ea2-930e-cfe8cecf1b6e",
      "values": [{ "LightPositionX_PointLight1": -10,
                       "LightPositionY_PointLight1": 0,
                       "LightPositionZ_PointLight1": 0 }]
    },
    {
      "capture_id": null,
      "annotation_id": null,
      "sequence_id": "405922af-9645-4f2a-a9b9-9cc70e5049f3",
      "step": 0,
      "metric_definition": "317735b9-b4a4-4f6b-a4c9-eb846463a583",
      "values": [{ "LightRotationX_PointLight1": 0,
                       "LightRotationY_PointLight1": 0,
                       "LightRotationZ_PointLight1": 0 }]
    },
    {
      "capture_id": null,
      "annotation_id": null,
      "sequence_id": "405922af-9645-4f2a-a9b9-9cc70e5049f3",
      "step": 0,
      "metric_definition": "1a709e09-81bd-43b5-b8f0-f3952a1af444",
      "values": [{ "LightIntensity_PointLight1": 23726.93 }]
    },
    {
      "capture_id": null,
      "annotation_id": null,
      "sequence_id": "405922af-9645-4f2a-a9b9-9cc70e5049f3",
      "step": 0,
      "metric_definition": "a640e390-fa13-4bb0-b2cd-1e0cb3f43eb9",
      "values": [{ "LightColorR_PointLight1": 0.2311927,
                       "LightColorG_PointLight1": 0.9741753,
                       "LightColorB_PointLight1": 0.170658,
                       "LightColorA_PointLight1": 1 }]
    },
    {
      "capture_id": null,
      "annotation_id": null,
      "sequence_id": "405922af-9645-4f2a-a9b9-9cc70e5049f3",
      "step": 0,
      "metric_definition": "c0b5e272-9715-4ea2-930e-cfe8cecf1b6e",
      "values": [{ "LightPositionX_PointLight2": 10,
                       "LightPositionY_PointLight2": 0,
                       "LightPositionZ_PointLight2": 0 }]
    },
    {
      "capture_id": null,
      "annotation_id": null,
      "sequence_id": "405922af-9645-4f2a-a9b9-9cc70e5049f3",
      "step": 0,
      "metric_definition": "317735b9-b4a4-4f6b-a4c9-eb846463a583",
      "values": [{ "LightRotationX_PointLight2": 0,
                       "LightRotationY_PointLight2": 0,
                       "LightRotationZ_PointLight2": 0 }]
    },
    {
      "capture_id": null,
      "annotation_id": null,
      "sequence_id": "405922af-9645-4f2a-a9b9-9cc70e5049f3",
      "step": 0,
      "metric_definition": "1a709e09-81bd-43b5-b8f0-f3952a1af444",
      "values": [{ "LightIntensity_PointLight2": 43135.68 }]
    },
    {
      "capture_id": null,
      "annotation_id": null,
      "sequence_id": "405922af-9645-4f2a-a9b9-9cc70e5049f3",
      "step": 0,
      "metric_definition": "a640e390-fa13-4bb0-b2cd-1e0cb3f43eb9",
      "values": [{ "LightColorR_PointLight2": 0.7126344,
                       "LightColorG_PointLight2": 0.7566602,
                       "LightColorB_PointLight2": 0.9453295,
                       "LightColorA_PointLight2": 1 }]
    },
    {
      "capture_id": null,
      "annotation_id": null,
      "sequence_id": "405922af-9645-4f2a-a9b9-9cc70e5049f3",
      "step": 0,
      "metric_definition": "c0b5e272-9715-4ea2-930e-cfe8cecf1b6e",
      "values": [{ "LightPositionX_PointLight3": 0,
                       "LightPositionY_PointLight3": 10,
                       "LightPositionZ_PointLight3": 0 }]
    },
    {
      "capture_id": null,
      "annotation_id": null,
      "sequence_id": "405922af-9645-4f2a-a9b9-9cc70e5049f3",
      "step": 0,
      "metric_definition": "317735b9-b4a4-4f6b-a4c9-eb846463a583",
      "values": [{ "LightRotationX_PointLight3": 0,
                       "LightRotationY_PointLight3": 0,
                       "LightRotationZ_PointLight3": 270 }]
    },
    {
      "capture_id": null,
      "annotation_id": null,
      "sequence_id": "405922af-9645-4f2a-a9b9-9cc70e5049f3",
      "step": 0,
      "metric_definition": "1a709e09-81bd-43b5-b8f0-f3952a1af444",
      "values": [{ "LightIntensity_PointLight3": 42438.13 }]
    },
    {
      "capture_id": null,
      "annotation_id": null,
      "sequence_id": "405922af-9645-4f2a-a9b9-9cc70e5049f3",
      "step": 0,
      "metric_definition": "a640e390-fa13-4bb0-b2cd-1e0cb3f43eb9",
      "values": [{ "LightColorR_PointLight3": 0.2992284,
                       "LightColorG_PointLight3": 0.03024912,
                       "LightColorB_PointLight3": 0.3367488,
                       "LightColorA_PointLight3": 1 }]
    },
    {
      "capture_id": null,
      "annotation_id": null,
      "sequence_id": "405922af-9645-4f2a-a9b9-9cc70e5049f3",
      "step": 0,
      "metric_definition": "c0b5e272-9715-4ea2-930e-cfe8cecf1b6e",
      "values": [{ "LightPositionX_PointLight4": 0,
                       "LightPositionY_PointLight4": -11,
                       "LightPositionZ_PointLight4": 0 }]
    },
    {
      "capture_id": null,
      "annotation_id": null,
      "sequence_id": "405922af-9645-4f2a-a9b9-9cc70e5049f3",
      "step": 0,
      "metric_definition": "317735b9-b4a4-4f6b-a4c9-eb846463a583",
      "values": [{ "LightRotationX_PointLight4": 0,
                       "LightRotationY_PointLight4": 0,
                       "LightRotationZ_PointLight4": 270 }]
    },
    {
      "capture_id": null,
      "annotation_id": null,
      "sequence_id": "405922af-9645-4f2a-a9b9-9cc70e5049f3",
      "step": 0,
      "metric_definition": "1a709e09-81bd-43b5-b8f0-f3952a1af444",
      "values": [{ "LightIntensity_PointLight4": 7235.729 }]
    },
    {
      "capture_id": null,
      "annotation_id": null,
      "sequence_id": "405922af-9645-4f2a-a9b9-9cc70e5049f3",
      "step": 0,
      "metric_definition": "a640e390-fa13-4bb0-b2cd-1e0cb3f43eb9",
      "values": [{ "LightColorR_PointLight4": 0.6782291,
                       "LightColorG_PointLight4": 0.04245985,
                       "LightColorB_PointLight4": 0.3867464,
                       "LightColorA_PointLight4": 1 }]
    },
    {
      "capture_id": null,
      "annotation_id": null,
      "sequence_id": "405922af-9645-4f2a-a9b9-9cc70e5049f3",
      "step": 0,
      "metric_definition": "c0b5e272-9715-4ea2-930e-cfe8cecf1b6e",
      "values": [{ "LightPositionX_PointLight5": 0,
                       "LightPositionY_PointLight5": 0,
                       "LightPositionZ_PointLight5": 10 }]
    },
    {
      "capture_id": null,
      "annotation_id": null,
      "sequence_id": "405922af-9645-4f2a-a9b9-9cc70e5049f3",
      "step": 0,
      "metric_definition": "317735b9-b4a4-4f6b-a4c9-eb846463a583",
      "values": [{ "LightRotationX_PointLight5": 90,
                       "LightRotationY_PointLight5": 89.99998,
                       "LightRotationZ_PointLight5": 0 }]
    },
    {
      "capture_id": null,
      "annotation_id": null,
      "sequence_id": "405922af-9645-4f2a-a9b9-9cc70e5049f3",
      "step": 0,
      "metric_definition": "1a709e09-81bd-43b5-b8f0-f3952a1af444",
      "values": [{ "LightIntensity_PointLight5": 32121.02 }]
    },
    {
      "capture_id": null,
      "annotation_id": null,
      "sequence_id": "405922af-9645-4f2a-a9b9-9cc70e5049f3",
      "step": 0,
      "metric_definition": "a640e390-fa13-4bb0-b2cd-1e0cb3f43eb9",
      "values": [{ "LightColorR_PointLight5": 0.8392804,
                       "LightColorG_PointLight5": 0.1640799,
                       "LightColorB_PointLight5": 0.8462288,
                       "LightColorA_PointLight5": 1 }]
    },
    {
      "capture_id": null,
      "annotation_id": null,
      "sequence_id": "405922af-9645-4f2a-a9b9-9cc70e5049f3",
      "step": 0,
      "metric_definition": "c0b5e272-9715-4ea2-930e-cfe8cecf1b6e",
      "values": [{ "LightPositionX_PointLight6": 0,
                       "LightPositionY_PointLight6": 0,
                       "LightPositionZ_PointLight6": -7 }]
    },
    {
      "capture_id": null,
      "annotation_id": null,
      "sequence_id": "405922af-9645-4f2a-a9b9-9cc70e5049f3",
      "step": 0,
      "metric_definition": "317735b9-b4a4-4f6b-a4c9-eb846463a583",
      "values": [{ "LightRotationX_PointLight6": 90,
                       "LightRotationY_PointLight6": 89.99998,
                       "LightRotationZ_PointLight6": 0 }]
    },
    {
      "capture_id": null,
      "annotation_id": null,
      "sequence_id": "405922af-9645-4f2a-a9b9-9cc70e5049f3",
      "step": 0,
      "metric_definition": "1a709e09-81bd-43b5-b8f0-f3952a1af444",
      "values": [{ "LightIntensity_PointLight6": 20384.16 }]
    },
    {
      "capture_id": null,
      "annotation_id": null,
      "sequence_id": "405922af-9645-4f2a-a9b9-9cc70e5049f3",
      "step": 0,
      "metric_definition": "a640e390-fa13-4bb0-b2cd-1e0cb3f43eb9",
      "values": [{ "LightColorR_PointLight6": 0.3082767,
                       "LightColorG_PointLight6": 0.4149244,
                       "LightColorB_PointLight6": 0.532548,
                       "LightColorA_PointLight6": 1 }]
    },
    {
      "capture_id": null,
      "annotation_id": null,
      "sequence_id": "405922af-9645-4f2a-a9b9-9cc70e5049f3",
      "step": 0,
      "metric_definition": "c0b5e272-9715-4ea2-930e-cfe8cecf1b6e",
      "values": [{ "LightPositionX_PointLightSceneMoving": 2.572036,
                       "LightPositionY_PointLightSceneMoving": 9.076215,
                       "LightPositionZ_PointLightSceneMoving": -0.06169558 }]
    },
    {
      "capture_id": null,
      "annotation_id": null,
      "sequence_id": "405922af-9645-4f2a-a9b9-9cc70e5049f3",
      "step": 0,
      "metric_definition": "317735b9-b4a4-4f6b-a4c9-eb846463a583",
      "values": [{ "LightRotationX_PointLightSceneMoving": 316.4166,
                       "LightRotationY_PointLightSceneMoving": 356.8773,
                       "LightRotationZ_PointLightSceneMoving": 339.5086 }]
    },
    {
      "capture_id": null,
      "annotation_id": null,
      "sequence_id": "405922af-9645-4f2a-a9b9-9cc70e5049f3",
      "step": 0,
      "metric_definition": "1a709e09-81bd-43b5-b8f0-f3952a1af444",
      "values": [{ "LightIntensity_PointLightSceneMoving": 35378.98 }]
    },
    {
      "capture_id": null,
      "annotation_id": null,
      "sequence_id": "405922af-9645-4f2a-a9b9-9cc70e5049f3",
      "step": 0,
      "metric_definition": "a640e390-fa13-4bb0-b2cd-1e0cb3f43eb9",
      "values": [{ "LightColorR_PointLightSceneMoving": 0.08790135,
                       "LightColorG_PointLightSceneMoving": 0.602095,
                       "LightColorB_PointLightSceneMoving": 0.8114325,
                       "LightColorA_PointLightSceneMoving": 1 }]
    },
    {
      "capture_id": null,
      "annotation_id": null,
      "sequence_id": "405922af-9645-4f2a-a9b9-9cc70e5049f3",
      "step": 0,
      "metric_definition": "1529faeb-863f-40c2-840f-5fe4221c1065",
      "values": [{ "CameraPositionX": 1.797734, "CameraPositionY": 0.5547047, "CameraPositionZ": 18.32668 }]
    },
    {
      "capture_id": null,
      "annotation_id": null,
      "sequence_id": "405922af-9645-4f2a-a9b9-9cc70e5049f3",
      "step": 0,
      "metric_definition": "5199deef-2eb0-42fe-b00d-1d2418aedaff",
      "values": [{ "CameraRotationX": 4.385751, "CameraRotationY": 180.8573, "CameraRotationZ": 1.456864 }]
    },
    {
      "capture_id": null,
      "annotation_id": null,
      "sequence_id": "405922af-9645-4f2a-a9b9-9cc70e5049f3",
      "step": 0,
      "metric_definition": "42e7fa88-084b-423d-ba6e-830c711383e1",
      "values": [{ "CameraFieldOfView": 18.66253 }]
    },
    {
      "capture_id": null,
      "annotation_id": null,
      "sequence_id": "405922af-9645-4f2a-a9b9-9cc70e5049f3",
      "step": 0,
      "metric_definition": "11aa1dfc-3495-467c-a998-71d9bfe6980e",
      "values": [{ "CameraFocalLength": 4.644752 }]
    },
    {
      "capture_id": "e1cdb2ea-e224-4732-a4a8-ad1b7c8cd9ea",
      "annotation_id": null,
      "sequence_id": "405922af-9645-4f2a-a9b9-9cc70e5049f3",
      "step": 0,
      "metric_definition": "51da3c27-369d-4929-aea6-d01614635ce2",
      "values": [
        {
          "label_id": 1,
          "label_name": "person",
          "count": 6
        }
      ]
    },
    {
      "capture_id": "e1cdb2ea-e224-4732-a4a8-ad1b7c8cd9ea",
      "annotation_id": null,
      "sequence_id": "405922af-9645-4f2a-a9b9-9cc70e5049f3",
      "step": 0,
      "metric_definition": "5ba92024-b3b7-41a7-9d3f-c03a6a8ddd01",
      "values": [
        {
          "label_id": 1,
          "instance_id": 28,
          "instance_color": {
            "r": 31,
            "g": 0,
            "b": 255,
            "a": 255
          },
          "visible_pixels": 1636
        },
        {
          "label_id": 1,
          "instance_id": 5,
          "instance_color": {
            "r": 0,
            "g": 255,
            "b": 212,
            "a": 255
          },
          "visible_pixels": 9
        },
        {
          "label_id": 1,
          "instance_id": 24,
          "instance_color": {
            "r": 181,
            "g": 255,
            "b": 0,
            "a": 255
          },
          "visible_pixels": 22483
        },
        {
          "label_id": 1,
          "instance_id": 22,
          "instance_color": {
            "r": 255,
            "g": 0,
            "b": 33,
            "a": 255
          },
          "visible_pixels": 23303
        },
        {
          "label_id": 1,
          "instance_id": 10,
          "instance_color": {
            "r": 0,
            "g": 160,
            "b": 255,
            "a": 255
          },
          "visible_pixels": 1641
        },
        {
          "label_id": 1,
          "instance_id": 21,
          "instance_color": {
            "r": 0,
            "g": 255,
            "b": 42,
            "a": 255
          },
          "visible_pixels": 2539
        }
      ]
    },
    {
      "capture_id": null,
      "annotation_id": null,
      "sequence_id": "50d7bf05-d0df-4d82-9106-1fe16cd289d2",
      "step": 0,
      "metric_definition": "db1b258e-d1d0-41b6-8751-16f601a2e230",
      "values": [
        {
          "iteration": 9
        }
      ]
    },
    {
      "capture_id": null,
      "annotation_id": null,
      "sequence_id": "50d7bf05-d0df-4d82-9106-1fe16cd289d2",
      "step": 0,
      "metric_definition": "c0b5e272-9715-4ea2-930e-cfe8cecf1b6e",
      "values": [{ "LightPositionX_DirectionalLightSun": 0,
                       "LightPositionY_DirectionalLightSun": 22,
                       "LightPositionZ_DirectionalLightSun": 14 }]
    },
    {
      "capture_id": null,
      "annotation_id": null,
      "sequence_id": "50d7bf05-d0df-4d82-9106-1fe16cd289d2",
      "step": 0,
      "metric_definition": "317735b9-b4a4-4f6b-a4c9-eb846463a583",
      "values": [{ "LightRotationX_DirectionalLightSun": 39.71478,
                       "LightRotationY_DirectionalLightSun": 142.2673,
                       "LightRotationZ_DirectionalLightSun": 141.734 }]
    },
    {
      "capture_id": null,
      "annotation_id": null,
      "sequence_id": "50d7bf05-d0df-4d82-9106-1fe16cd289d2",
      "step": 0,
      "metric_definition": "1a709e09-81bd-43b5-b8f0-f3952a1af444",
      "values": [{ "LightIntensity_DirectionalLightSun": 10000 }]
    },
    {
      "capture_id": null,
      "annotation_id": null,
      "sequence_id": "50d7bf05-d0df-4d82-9106-1fe16cd289d2",
      "step": 0,
      "metric_definition": "a640e390-fa13-4bb0-b2cd-1e0cb3f43eb9",
      "values": [{ "LightColorR_DirectionalLightSun": 1,
                       "LightColorG_DirectionalLightSun": 0.9568627,
                       "LightColorB_DirectionalLightSun": 0.8392157,
                       "LightColorA_DirectionalLightSun": 1 }]
    },
    {
      "capture_id": null,
      "annotation_id": null,
      "sequence_id": "50d7bf05-d0df-4d82-9106-1fe16cd289d2",
      "step": 0,
      "metric_definition": "c0b5e272-9715-4ea2-930e-cfe8cecf1b6e",
      "values": [{ "LightPositionX_PointLight1": -10,
                       "LightPositionY_PointLight1": 0,
                       "LightPositionZ_PointLight1": 0 }]
    },
    {
      "capture_id": null,
      "annotation_id": null,
      "sequence_id": "50d7bf05-d0df-4d82-9106-1fe16cd289d2",
      "step": 0,
      "metric_definition": "317735b9-b4a4-4f6b-a4c9-eb846463a583",
      "values": [{ "LightRotationX_PointLight1": 0,
                       "LightRotationY_PointLight1": 0,
                       "LightRotationZ_PointLight1": 0 }]
    },
    {
      "capture_id": null,
      "annotation_id": null,
      "sequence_id": "50d7bf05-d0df-4d82-9106-1fe16cd289d2",
      "step": 0,
      "metric_definition": "1a709e09-81bd-43b5-b8f0-f3952a1af444",
      "values": [{ "LightIntensity_PointLight1": 47389.06 }]
    },
    {
      "capture_id": null,
      "annotation_id": null,
      "sequence_id": "50d7bf05-d0df-4d82-9106-1fe16cd289d2",
      "step": 0,
      "metric_definition": "a640e390-fa13-4bb0-b2cd-1e0cb3f43eb9",
      "values": [{ "LightColorR_PointLight1": 0.1470985,
                       "LightColorG_PointLight1": 0.1143095,
                       "LightColorB_PointLight1": 0.8328648,
                       "LightColorA_PointLight1": 1 }]
    },
    {
      "capture_id": null,
      "annotation_id": null,
      "sequence_id": "50d7bf05-d0df-4d82-9106-1fe16cd289d2",
      "step": 0,
      "metric_definition": "c0b5e272-9715-4ea2-930e-cfe8cecf1b6e",
      "values": [{ "LightPositionX_PointLight2": 10,
                       "LightPositionY_PointLight2": 0,
                       "LightPositionZ_PointLight2": 0 }]
    },
    {
      "capture_id": null,
      "annotation_id": null,
      "sequence_id": "50d7bf05-d0df-4d82-9106-1fe16cd289d2",
      "step": 0,
      "metric_definition": "317735b9-b4a4-4f6b-a4c9-eb846463a583",
      "values": [{ "LightRotationX_PointLight2": 0,
                       "LightRotationY_PointLight2": 0,
                       "LightRotationZ_PointLight2": 0 }]
    },
    {
      "capture_id": null,
      "annotation_id": null,
      "sequence_id": "50d7bf05-d0df-4d82-9106-1fe16cd289d2",
      "step": 0,
      "metric_definition": "1a709e09-81bd-43b5-b8f0-f3952a1af444",
      "values": [{ "LightIntensity_PointLight2": 5534.398 }]
    },
    {
      "capture_id": null,
      "annotation_id": null,
      "sequence_id": "50d7bf05-d0df-4d82-9106-1fe16cd289d2",
      "step": 0,
      "metric_definition": "a640e390-fa13-4bb0-b2cd-1e0cb3f43eb9",
      "values": [{ "LightColorR_PointLight2": 0.09783876,
                       "LightColorG_PointLight2": 0.728726,
                       "LightColorB_PointLight2": 0.1797588,
                       "LightColorA_PointLight2": 1 }]
    },
    {
      "capture_id": null,
      "annotation_id": null,
      "sequence_id": "50d7bf05-d0df-4d82-9106-1fe16cd289d2",
      "step": 0,
      "metric_definition": "c0b5e272-9715-4ea2-930e-cfe8cecf1b6e",
      "values": [{ "LightPositionX_PointLight3": 0,
                       "LightPositionY_PointLight3": 10,
                       "LightPositionZ_PointLight3": 0 }]
    },
    {
      "capture_id": null,
      "annotation_id": null,
      "sequence_id": "50d7bf05-d0df-4d82-9106-1fe16cd289d2",
      "step": 0,
      "metric_definition": "317735b9-b4a4-4f6b-a4c9-eb846463a583",
      "values": [{ "LightRotationX_PointLight3": 0,
                       "LightRotationY_PointLight3": 0,
                       "LightRotationZ_PointLight3": 270 }]
    },
    {
      "capture_id": null,
      "annotation_id": null,
      "sequence_id": "50d7bf05-d0df-4d82-9106-1fe16cd289d2",
      "step": 0,
      "metric_definition": "1a709e09-81bd-43b5-b8f0-f3952a1af444",
      "values": [{ "LightIntensity_PointLight3": 35837.41 }]
    },
    {
      "capture_id": null,
      "annotation_id": null,
      "sequence_id": "50d7bf05-d0df-4d82-9106-1fe16cd289d2",
      "step": 0,
      "metric_definition": "a640e390-fa13-4bb0-b2cd-1e0cb3f43eb9",
      "values": [{ "LightColorR_PointLight3": 0.582646,
                       "LightColorG_PointLight3": 0.3311089,
                       "LightColorB_PointLight3": 0.03703213,
                       "LightColorA_PointLight3": 1 }]
    },
    {
      "capture_id": null,
      "annotation_id": null,
      "sequence_id": "50d7bf05-d0df-4d82-9106-1fe16cd289d2",
      "step": 0,
      "metric_definition": "c0b5e272-9715-4ea2-930e-cfe8cecf1b6e",
      "values": [{ "LightPositionX_PointLight4": 0,
                       "LightPositionY_PointLight4": -11,
                       "LightPositionZ_PointLight4": 0 }]
    },
    {
      "capture_id": null,
      "annotation_id": null,
      "sequence_id": "50d7bf05-d0df-4d82-9106-1fe16cd289d2",
      "step": 0,
      "metric_definition": "317735b9-b4a4-4f6b-a4c9-eb846463a583",
      "values": [{ "LightRotationX_PointLight4": 0,
                       "LightRotationY_PointLight4": 0,
                       "LightRotationZ_PointLight4": 270 }]
    },
    {
      "capture_id": null,
      "annotation_id": null,
      "sequence_id": "50d7bf05-d0df-4d82-9106-1fe16cd289d2",
      "step": 0,
      "metric_definition": "1a709e09-81bd-43b5-b8f0-f3952a1af444",
      "values": [{ "LightIntensity_PointLight4": 18586.76 }]
    },
    {
      "capture_id": null,
      "annotation_id": null,
      "sequence_id": "50d7bf05-d0df-4d82-9106-1fe16cd289d2",
      "step": 0,
      "metric_definition": "a640e390-fa13-4bb0-b2cd-1e0cb3f43eb9",
      "values": [{ "LightColorR_PointLight4": 0.5355039,
                       "LightColorG_PointLight4": 0.09054232,
                       "LightColorB_PointLight4": 0.4692794,
                       "LightColorA_PointLight4": 1 }]
    },
    {
      "capture_id": null,
      "annotation_id": null,
      "sequence_id": "50d7bf05-d0df-4d82-9106-1fe16cd289d2",
      "step": 0,
      "metric_definition": "c0b5e272-9715-4ea2-930e-cfe8cecf1b6e",
      "values": [{ "LightPositionX_PointLight5": 0,
                       "LightPositionY_PointLight5": 0,
                       "LightPositionZ_PointLight5": 10 }]
    },
    {
      "capture_id": null,
      "annotation_id": null,
      "sequence_id": "50d7bf05-d0df-4d82-9106-1fe16cd289d2",
      "step": 0,
      "metric_definition": "317735b9-b4a4-4f6b-a4c9-eb846463a583",
      "values": [{ "LightRotationX_PointLight5": 90,
                       "LightRotationY_PointLight5": 89.99998,
                       "LightRotationZ_PointLight5": 0 }]
    },
    {
      "capture_id": null,
      "annotation_id": null,
      "sequence_id": "50d7bf05-d0df-4d82-9106-1fe16cd289d2",
      "step": 0,
      "metric_definition": "1a709e09-81bd-43b5-b8f0-f3952a1af444",
      "values": [{ "LightIntensity_PointLight5": 23089.32 }]
    },
    {
      "capture_id": null,
      "annotation_id": null,
      "sequence_id": "50d7bf05-d0df-4d82-9106-1fe16cd289d2",
      "step": 0,
      "metric_definition": "a640e390-fa13-4bb0-b2cd-1e0cb3f43eb9",
      "values": [{ "LightColorR_PointLight5": 0.9727558,
                       "LightColorG_PointLight5": 0.4253441,
                       "LightColorB_PointLight5": 0.9006395,
                       "LightColorA_PointLight5": 1 }]
    },
    {
      "capture_id": null,
      "annotation_id": null,
      "sequence_id": "50d7bf05-d0df-4d82-9106-1fe16cd289d2",
      "step": 0,
      "metric_definition": "c0b5e272-9715-4ea2-930e-cfe8cecf1b6e",
      "values": [{ "LightPositionX_PointLight6": 0,
                       "LightPositionY_PointLight6": 0,
                       "LightPositionZ_PointLight6": -7 }]
    },
    {
      "capture_id": null,
      "annotation_id": null,
      "sequence_id": "50d7bf05-d0df-4d82-9106-1fe16cd289d2",
      "step": 0,
      "metric_definition": "317735b9-b4a4-4f6b-a4c9-eb846463a583",
      "values": [{ "LightRotationX_PointLight6": 90,
                       "LightRotationY_PointLight6": 89.99998,
                       "LightRotationZ_PointLight6": 0 }]
    },
    {
      "capture_id": null,
      "annotation_id": null,
      "sequence_id": "50d7bf05-d0df-4d82-9106-1fe16cd289d2",
      "step": 0,
      "metric_definition": "1a709e09-81bd-43b5-b8f0-f3952a1af444",
      "values": [{ "LightIntensity_PointLight6": 44339.22 }]
    },
    {
      "capture_id": null,
      "annotation_id": null,
      "sequence_id": "50d7bf05-d0df-4d82-9106-1fe16cd289d2",
      "step": 0,
      "metric_definition": "a640e390-fa13-4bb0-b2cd-1e0cb3f43eb9",
      "values": [{ "LightColorR_PointLight6": 0.113022,
                       "LightColorG_PointLight6": 0.09110475,
                       "LightColorB_PointLight6": 0.4261751,
                       "LightColorA_PointLight6": 1 }]
    },
    {
      "capture_id": null,
      "annotation_id": null,
      "sequence_id": "50d7bf05-d0df-4d82-9106-1fe16cd289d2",
      "step": 0,
      "metric_definition": "c0b5e272-9715-4ea2-930e-cfe8cecf1b6e",
      "values": [{ "LightPositionX_PointLightSceneMoving": -2.496893,
                       "LightPositionY_PointLightSceneMoving": 9.267191,
                       "LightPositionZ_PointLightSceneMoving": -0.3564782 }]
    },
    {
      "capture_id": null,
      "annotation_id": null,
      "sequence_id": "50d7bf05-d0df-4d82-9106-1fe16cd289d2",
      "step": 0,
      "metric_definition": "317735b9-b4a4-4f6b-a4c9-eb846463a583",
      "values": [{ "LightRotationX_PointLightSceneMoving": 340.318,
                       "LightRotationY_PointLightSceneMoving": 47.71319,
                       "LightRotationZ_PointLightSceneMoving": 37.65446 }]
    },
    {
      "capture_id": null,
      "annotation_id": null,
      "sequence_id": "50d7bf05-d0df-4d82-9106-1fe16cd289d2",
      "step": 0,
      "metric_definition": "1a709e09-81bd-43b5-b8f0-f3952a1af444",
      "values": [{ "LightIntensity_PointLightSceneMoving": 19364.24 }]
    },
    {
      "capture_id": null,
      "annotation_id": null,
      "sequence_id": "50d7bf05-d0df-4d82-9106-1fe16cd289d2",
      "step": 0,
      "metric_definition": "a640e390-fa13-4bb0-b2cd-1e0cb3f43eb9",
      "values": [{ "LightColorR_PointLightSceneMoving": 0.259645,
                       "LightColorG_PointLightSceneMoving": 0.8562009,
                       "LightColorB_PointLightSceneMoving": 0.8741308,
                       "LightColorA_PointLightSceneMoving": 1 }]
    },
    {
      "capture_id": null,
      "annotation_id": null,
      "sequence_id": "50d7bf05-d0df-4d82-9106-1fe16cd289d2",
      "step": 0,
      "metric_definition": "1529faeb-863f-40c2-840f-5fe4221c1065",
      "values": [{ "CameraPositionX": -2.755474, "CameraPositionY": -2.596367, "CameraPositionZ": 14.45052 }]
    },
    {
      "capture_id": null,
      "annotation_id": null,
      "sequence_id": "50d7bf05-d0df-4d82-9106-1fe16cd289d2",
      "step": 0,
      "metric_definition": "5199deef-2eb0-42fe-b00d-1d2418aedaff",
      "values": [{ "CameraRotationX": 3.279716, "CameraRotationY": 183.0225, "CameraRotationZ": 356.4555 }]
    },
    {
      "capture_id": null,
      "annotation_id": null,
      "sequence_id": "50d7bf05-d0df-4d82-9106-1fe16cd289d2",
      "step": 0,
      "metric_definition": "42e7fa88-084b-423d-ba6e-830c711383e1",
      "values": [{ "CameraFieldOfView": 38.36536 }]
    },
    {
      "capture_id": null,
      "annotation_id": null,
      "sequence_id": "50d7bf05-d0df-4d82-9106-1fe16cd289d2",
      "step": 0,
      "metric_definition": "11aa1dfc-3495-467c-a998-71d9bfe6980e",
      "values": [{ "CameraFocalLength": 19.3945 }]
    },
    {
      "capture_id": "556c3b44-14fb-46a3-a3c3-00e4ab119894",
      "annotation_id": null,
      "sequence_id": "50d7bf05-d0df-4d82-9106-1fe16cd289d2",
      "step": 0,
      "metric_definition": "51da3c27-369d-4929-aea6-d01614635ce2",
      "values": [
        {
          "label_id": 1,
          "label_name": "person",
          "count": 8
        }
      ]
    },
    {
      "capture_id": "556c3b44-14fb-46a3-a3c3-00e4ab119894",
      "annotation_id": null,
      "sequence_id": "50d7bf05-d0df-4d82-9106-1fe16cd289d2",
      "step": 0,
      "metric_definition": "5ba92024-b3b7-41a7-9d3f-c03a6a8ddd01",
      "values": [
        {
          "label_id": 1,
          "instance_id": 16,
          "instance_color": {
            "r": 96,
            "g": 255,
            "b": 0,
            "a": 255
          },
          "visible_pixels": 104
        },
        {
          "label_id": 1,
          "instance_id": 3,
          "instance_color": {
            "r": 149,
            "g": 255,
            "b": 0,
            "a": 255
          },
          "visible_pixels": 2859
        },
        {
          "label_id": 1,
          "instance_id": 35,
          "instance_color": {
            "r": 255,
            "g": 20,
            "b": 0,
            "a": 255
          },
          "visible_pixels": 6411
        },
        {
          "label_id": 1,
          "instance_id": 22,
          "instance_color": {
            "r": 255,
            "g": 0,
            "b": 33,
            "a": 255
          },
          "visible_pixels": 3716
        },
        {
          "label_id": 1,
          "instance_id": 8,
          "instance_color": {
            "r": 11,
            "g": 255,
            "b": 0,
            "a": 255
          },
          "visible_pixels": 6449
        },
        {
          "label_id": 1,
          "instance_id": 24,
          "instance_color": {
            "r": 181,
            "g": 255,
            "b": 0,
            "a": 255
          },
          "visible_pixels": 2218
        },
        {
          "label_id": 1,
          "instance_id": 33,
          "instance_color": {
            "r": 169,
            "g": 0,
            "b": 255,
            "a": 255
          },
          "visible_pixels": 4813
        },
        {
          "label_id": 1,
          "instance_id": 36,
          "instance_color": {
            "r": 0,
            "g": 54,
            "b": 255,
            "a": 255
          },
          "visible_pixels": 929
        }
      ]
    },
    {
      "capture_id": null,
      "annotation_id": null,
      "sequence_id": "ab88f9ec-f2dd-4872-9b0a-117fad39aa99",
      "step": 0,
      "metric_definition": "db1b258e-d1d0-41b6-8751-16f601a2e230",
      "values": [
        {
          "iteration": 10
        }
      ]
    },
    {
      "capture_id": null,
      "annotation_id": null,
      "sequence_id": "ab88f9ec-f2dd-4872-9b0a-117fad39aa99",
      "step": 0,
      "metric_definition": "c0b5e272-9715-4ea2-930e-cfe8cecf1b6e",
      "values": [{ "LightPositionX_DirectionalLightSun": 0,
                       "LightPositionY_DirectionalLightSun": 22,
                       "LightPositionZ_DirectionalLightSun": 14 }]
    },
    {
      "capture_id": null,
      "annotation_id": null,
      "sequence_id": "ab88f9ec-f2dd-4872-9b0a-117fad39aa99",
      "step": 0,
      "metric_definition": "317735b9-b4a4-4f6b-a4c9-eb846463a583",
      "values": [{ "LightRotationX_DirectionalLightSun": 12.81672,
                       "LightRotationY_DirectionalLightSun": 329.3381,
                       "LightRotationZ_DirectionalLightSun": 343.3714 }]
    },
    {
      "capture_id": null,
      "annotation_id": null,
      "sequence_id": "ab88f9ec-f2dd-4872-9b0a-117fad39aa99",
      "step": 0,
      "metric_definition": "1a709e09-81bd-43b5-b8f0-f3952a1af444",
      "values": [{ "LightIntensity_DirectionalLightSun": 10000 }]
    },
    {
      "capture_id": null,
      "annotation_id": null,
      "sequence_id": "ab88f9ec-f2dd-4872-9b0a-117fad39aa99",
      "step": 0,
      "metric_definition": "a640e390-fa13-4bb0-b2cd-1e0cb3f43eb9",
      "values": [{ "LightColorR_DirectionalLightSun": 1,
                       "LightColorG_DirectionalLightSun": 0.9568627,
                       "LightColorB_DirectionalLightSun": 0.8392157,
                       "LightColorA_DirectionalLightSun": 1 }]
    },
    {
      "capture_id": null,
      "annotation_id": null,
      "sequence_id": "ab88f9ec-f2dd-4872-9b0a-117fad39aa99",
      "step": 0,
      "metric_definition": "c0b5e272-9715-4ea2-930e-cfe8cecf1b6e",
      "values": [{ "LightPositionX_PointLight1": -10,
                       "LightPositionY_PointLight1": 0,
                       "LightPositionZ_PointLight1": 0 }]
    },
    {
      "capture_id": null,
      "annotation_id": null,
      "sequence_id": "ab88f9ec-f2dd-4872-9b0a-117fad39aa99",
      "step": 0,
      "metric_definition": "317735b9-b4a4-4f6b-a4c9-eb846463a583",
      "values": [{ "LightRotationX_PointLight1": 0,
                       "LightRotationY_PointLight1": 0,
                       "LightRotationZ_PointLight1": 0 }]
    },
    {
      "capture_id": null,
      "annotation_id": null,
      "sequence_id": "ab88f9ec-f2dd-4872-9b0a-117fad39aa99",
      "step": 0,
      "metric_definition": "1a709e09-81bd-43b5-b8f0-f3952a1af444",
      "values": [{ "LightIntensity_PointLight1": 29216.31 }]
    },
    {
      "capture_id": null,
      "annotation_id": null,
      "sequence_id": "ab88f9ec-f2dd-4872-9b0a-117fad39aa99",
      "step": 0,
      "metric_definition": "a640e390-fa13-4bb0-b2cd-1e0cb3f43eb9",
      "values": [{ "LightColorR_PointLight1": 0.9082211,
                       "LightColorG_PointLight1": 0.4640017,
                       "LightColorB_PointLight1": 0.07929695,
                       "LightColorA_PointLight1": 1 }]
    },
    {
      "capture_id": null,
      "annotation_id": null,
      "sequence_id": "ab88f9ec-f2dd-4872-9b0a-117fad39aa99",
      "step": 0,
      "metric_definition": "c0b5e272-9715-4ea2-930e-cfe8cecf1b6e",
      "values": [{ "LightPositionX_PointLight2": 10,
                       "LightPositionY_PointLight2": 0,
                       "LightPositionZ_PointLight2": 0 }]
    },
    {
      "capture_id": null,
      "annotation_id": null,
      "sequence_id": "ab88f9ec-f2dd-4872-9b0a-117fad39aa99",
      "step": 0,
      "metric_definition": "317735b9-b4a4-4f6b-a4c9-eb846463a583",
      "values": [{ "LightRotationX_PointLight2": 0,
                       "LightRotationY_PointLight2": 0,
                       "LightRotationZ_PointLight2": 0 }]
    },
    {
      "capture_id": null,
      "annotation_id": null,
      "sequence_id": "ab88f9ec-f2dd-4872-9b0a-117fad39aa99",
      "step": 0,
      "metric_definition": "1a709e09-81bd-43b5-b8f0-f3952a1af444",
      "values": [{ "LightIntensity_PointLight2": 9762.911 }]
    },
    {
      "capture_id": null,
      "annotation_id": null,
      "sequence_id": "ab88f9ec-f2dd-4872-9b0a-117fad39aa99",
      "step": 0,
      "metric_definition": "a640e390-fa13-4bb0-b2cd-1e0cb3f43eb9",
      "values": [{ "LightColorR_PointLight2": 0.1626102,
                       "LightColorG_PointLight2": 0.2913518,
                       "LightColorB_PointLight2": 0.06079245,
                       "LightColorA_PointLight2": 1 }]
    },
    {
      "capture_id": null,
      "annotation_id": null,
      "sequence_id": "ab88f9ec-f2dd-4872-9b0a-117fad39aa99",
      "step": 0,
      "metric_definition": "c0b5e272-9715-4ea2-930e-cfe8cecf1b6e",
      "values": [{ "LightPositionX_PointLight3": 0,
                       "LightPositionY_PointLight3": 10,
                       "LightPositionZ_PointLight3": 0 }]
    },
    {
      "capture_id": null,
      "annotation_id": null,
      "sequence_id": "ab88f9ec-f2dd-4872-9b0a-117fad39aa99",
      "step": 0,
      "metric_definition": "317735b9-b4a4-4f6b-a4c9-eb846463a583",
      "values": [{ "LightRotationX_PointLight3": 0,
                       "LightRotationY_PointLight3": 0,
                       "LightRotationZ_PointLight3": 270 }]
    },
    {
      "capture_id": null,
      "annotation_id": null,
      "sequence_id": "ab88f9ec-f2dd-4872-9b0a-117fad39aa99",
      "step": 0,
      "metric_definition": "1a709e09-81bd-43b5-b8f0-f3952a1af444",
      "values": [{ "LightIntensity_PointLight3": 32887.74 }]
    },
    {
      "capture_id": null,
      "annotation_id": null,
      "sequence_id": "ab88f9ec-f2dd-4872-9b0a-117fad39aa99",
      "step": 0,
      "metric_definition": "a640e390-fa13-4bb0-b2cd-1e0cb3f43eb9",
      "values": [{ "LightColorR_PointLight3": 0.02851927,
                       "LightColorG_PointLight3": 0.2552184,
                       "LightColorB_PointLight3": 0.4206345,
                       "LightColorA_PointLight3": 1 }]
    },
    {
      "capture_id": null,
      "annotation_id": null,
      "sequence_id": "ab88f9ec-f2dd-4872-9b0a-117fad39aa99",
      "step": 0,
      "metric_definition": "c0b5e272-9715-4ea2-930e-cfe8cecf1b6e",
      "values": [{ "LightPositionX_PointLight4": 0,
                       "LightPositionY_PointLight4": -11,
                       "LightPositionZ_PointLight4": 0 }]
    },
    {
      "capture_id": null,
      "annotation_id": null,
      "sequence_id": "ab88f9ec-f2dd-4872-9b0a-117fad39aa99",
      "step": 0,
      "metric_definition": "317735b9-b4a4-4f6b-a4c9-eb846463a583",
      "values": [{ "LightRotationX_PointLight4": 0,
                       "LightRotationY_PointLight4": 0,
                       "LightRotationZ_PointLight4": 270 }]
    },
    {
      "capture_id": null,
      "annotation_id": null,
      "sequence_id": "ab88f9ec-f2dd-4872-9b0a-117fad39aa99",
      "step": 0,
      "metric_definition": "1a709e09-81bd-43b5-b8f0-f3952a1af444",
      "values": [{ "LightIntensity_PointLight4": 18902.81 }]
    },
    {
      "capture_id": null,
      "annotation_id": null,
      "sequence_id": "ab88f9ec-f2dd-4872-9b0a-117fad39aa99",
      "step": 0,
      "metric_definition": "a640e390-fa13-4bb0-b2cd-1e0cb3f43eb9",
      "values": [{ "LightColorR_PointLight4": 0.1400881,
                       "LightColorG_PointLight4": 0.05135798,
                       "LightColorB_PointLight4": 0.3240299,
                       "LightColorA_PointLight4": 1 }]
    },
    {
      "capture_id": null,
      "annotation_id": null,
      "sequence_id": "ab88f9ec-f2dd-4872-9b0a-117fad39aa99",
      "step": 0,
      "metric_definition": "c0b5e272-9715-4ea2-930e-cfe8cecf1b6e",
      "values": [{ "LightPositionX_PointLight5": 0,
                       "LightPositionY_PointLight5": 0,
                       "LightPositionZ_PointLight5": 10 }]
    },
    {
      "capture_id": null,
      "annotation_id": null,
      "sequence_id": "ab88f9ec-f2dd-4872-9b0a-117fad39aa99",
      "step": 0,
      "metric_definition": "317735b9-b4a4-4f6b-a4c9-eb846463a583",
      "values": [{ "LightRotationX_PointLight5": 90,
                       "LightRotationY_PointLight5": 89.99998,
                       "LightRotationZ_PointLight5": 0 }]
    },
    {
      "capture_id": null,
      "annotation_id": null,
      "sequence_id": "ab88f9ec-f2dd-4872-9b0a-117fad39aa99",
      "step": 0,
      "metric_definition": "1a709e09-81bd-43b5-b8f0-f3952a1af444",
      "values": [{ "LightIntensity_PointLight5": 41525.9 }]
    },
    {
      "capture_id": null,
      "annotation_id": null,
      "sequence_id": "ab88f9ec-f2dd-4872-9b0a-117fad39aa99",
      "step": 0,
      "metric_definition": "a640e390-fa13-4bb0-b2cd-1e0cb3f43eb9",
      "values": [{ "LightColorR_PointLight5": 0.9807872,
                       "LightColorG_PointLight5": 0.04659545,
                       "LightColorB_PointLight5": 0.703156,
                       "LightColorA_PointLight5": 1 }]
    },
    {
      "capture_id": null,
      "annotation_id": null,
      "sequence_id": "ab88f9ec-f2dd-4872-9b0a-117fad39aa99",
      "step": 0,
      "metric_definition": "c0b5e272-9715-4ea2-930e-cfe8cecf1b6e",
      "values": [{ "LightPositionX_PointLight6": 0,
                       "LightPositionY_PointLight6": 0,
                       "LightPositionZ_PointLight6": -7 }]
    },
    {
      "capture_id": null,
      "annotation_id": null,
      "sequence_id": "ab88f9ec-f2dd-4872-9b0a-117fad39aa99",
      "step": 0,
      "metric_definition": "317735b9-b4a4-4f6b-a4c9-eb846463a583",
      "values": [{ "LightRotationX_PointLight6": 90,
                       "LightRotationY_PointLight6": 89.99998,
                       "LightRotationZ_PointLight6": 0 }]
    },
    {
      "capture_id": null,
      "annotation_id": null,
      "sequence_id": "ab88f9ec-f2dd-4872-9b0a-117fad39aa99",
      "step": 0,
      "metric_definition": "1a709e09-81bd-43b5-b8f0-f3952a1af444",
      "values": [{ "LightIntensity_PointLight6": 15722.6 }]
    },
    {
      "capture_id": null,
      "annotation_id": null,
      "sequence_id": "ab88f9ec-f2dd-4872-9b0a-117fad39aa99",
      "step": 0,
      "metric_definition": "a640e390-fa13-4bb0-b2cd-1e0cb3f43eb9",
      "values": [{ "LightColorR_PointLight6": 0.1896052,
                       "LightColorG_PointLight6": 0.8911823,
                       "LightColorB_PointLight6": 0.6823118,
                       "LightColorA_PointLight6": 1 }]
    },
    {
      "capture_id": null,
      "annotation_id": null,
      "sequence_id": "ab88f9ec-f2dd-4872-9b0a-117fad39aa99",
      "step": 0,
      "metric_definition": "c0b5e272-9715-4ea2-930e-cfe8cecf1b6e",
      "values": [{ "LightPositionX_PointLightSceneMoving": -2.181252,
                       "LightPositionY_PointLightSceneMoving": 6.4256,
                       "LightPositionZ_PointLightSceneMoving": 3.779329 }]
    },
    {
      "capture_id": null,
      "annotation_id": null,
      "sequence_id": "ab88f9ec-f2dd-4872-9b0a-117fad39aa99",
      "step": 0,
      "metric_definition": "317735b9-b4a4-4f6b-a4c9-eb846463a583",
      "values": [{ "LightRotationX_PointLightSceneMoving": 23.68169,
                       "LightRotationY_PointLightSceneMoving": 356.0874,
                       "LightRotationZ_PointLightSceneMoving": 333.6674 }]
    },
    {
      "capture_id": null,
      "annotation_id": null,
      "sequence_id": "ab88f9ec-f2dd-4872-9b0a-117fad39aa99",
      "step": 0,
      "metric_definition": "1a709e09-81bd-43b5-b8f0-f3952a1af444",
      "values": [{ "LightIntensity_PointLightSceneMoving": 42985.64 }]
    },
    {
      "capture_id": null,
      "annotation_id": null,
      "sequence_id": "ab88f9ec-f2dd-4872-9b0a-117fad39aa99",
      "step": 0,
      "metric_definition": "a640e390-fa13-4bb0-b2cd-1e0cb3f43eb9",
      "values": [{ "LightColorR_PointLightSceneMoving": 0.9811521,
                       "LightColorG_PointLightSceneMoving": 0.3254113,
                       "LightColorB_PointLightSceneMoving": 0.8679885,
                       "LightColorA_PointLightSceneMoving": 1 }]
    },
    {
      "capture_id": null,
      "annotation_id": null,
      "sequence_id": "ab88f9ec-f2dd-4872-9b0a-117fad39aa99",
      "step": 0,
      "metric_definition": "1529faeb-863f-40c2-840f-5fe4221c1065",
      "values": [{ "CameraPositionX": 4.895547, "CameraPositionY": -1.272612, "CameraPositionZ": 19.3363 }]
    },
    {
      "capture_id": null,
      "annotation_id": null,
      "sequence_id": "ab88f9ec-f2dd-4872-9b0a-117fad39aa99",
      "step": 0,
      "metric_definition": "5199deef-2eb0-42fe-b00d-1d2418aedaff",
      "values": [{ "CameraRotationX": 355.8658, "CameraRotationY": 180.8917, "CameraRotationZ": 2.5848 }]
    },
    {
      "capture_id": null,
      "annotation_id": null,
      "sequence_id": "ab88f9ec-f2dd-4872-9b0a-117fad39aa99",
      "step": 0,
      "metric_definition": "42e7fa88-084b-423d-ba6e-830c711383e1",
      "values": [{ "CameraFieldOfView": 25.29357 }]
    },
    {
      "capture_id": null,
      "annotation_id": null,
      "sequence_id": "ab88f9ec-f2dd-4872-9b0a-117fad39aa99",
      "step": 0,
      "metric_definition": "11aa1dfc-3495-467c-a998-71d9bfe6980e",
      "values": [{ "CameraFocalLength": 21.52654 }]
    }
  ]
}